[{"title":"第一章 诡异的包裹","id":"6062400"},{"title":"第二章 神秘访客","id":"6062401"},{"title":"第三章 午夜空白短信 为打赏50元人民币大保健的思思加更~！","id":"6062402"},{"title":"第四章 远赴草原","id":"6062403"},{"title":"第五章 火车呓语","id":"6062404"},{"title":"第六章 被活埋（上）","id":"6062405"},{"title":"第七章 被活埋（下）","id":"6062406"},{"title":"第八章 回忆片段","id":"6062407"},{"title":"第九章 假冒的身份（上） 感谢七哥打赏玉佩，么么哒~","id":"6062408"},{"title":"第十章 假冒的身份（下）","id":"6062409"},{"title":"第十一章 殉葬鬼影","id":"6062410"},{"title":"第十二章 亦敌亦友","id":"6062411"},{"title":"第十三章 神秘的白衣女人","id":"6062412"},{"title":"第十四章 闫至阳的过往","id":"6062413"},{"title":"第十五章 情仇一线","id":"6062414"},{"title":"第十六章 不要脸的交换 感谢兰陵王跟言语的打赏~！加更~！","id":"6062415"},{"title":"第十七章 闫家的请帖（上）","id":"6062416"},{"title":"第十八章 闫家的请帖（下）","id":"6062417"},{"title":"第十九章 闫至阳的说辞","id":"6062418"},{"title":"第二十章 尘封的记忆","id":"6062419"},{"title":"第二十一章 凶物店","id":"6062420"},{"title":"第二十二章 十八铜娃娃的诡异凶事（上）","id":"6062421"},{"title":"第二十三章 十八铜娃娃的诡异凶事（下） 既然网站有推荐，就加更一章吧。谢谢支持","id":"6062422"},{"title":"第二十四章 嫉妒之罪","id":"6062423"},{"title":"第二十五章 送子骗子刘大师","id":"6062424"},{"title":"第二十六章 封灵契的秘密（上）","id":"6062425"},{"title":"第二十七章 封灵契的秘密（下）","id":"6062426"},{"title":"第二十八章 释疑","id":"6062427"},{"title":"第二十九章 红色锦盒里的秘密","id":"6062428"},{"title":"第三十章 鬼快递（上）","id":"6062429"},{"title":"第三十一章 鬼快递（下）","id":"6062430"},{"title":"第三十二章 刘大师的下落","id":"6062431"},{"title":"第三十三章 活捉刘大师","id":"6062432"},{"title":"第三十四章 破碎的金盘","id":"6062433"},{"title":"第三十五章 好色快递鬼","id":"6062434"},{"title":"第三十六章 群棺倩影（上）","id":"6062435"},{"title":"第三十七章 群棺倩影（下）","id":"6062436"},{"title":"第三十八章 遇袭（上）","id":"6062437"},{"title":"第三十九章 遇袭（下）","id":"6062438"},{"title":"第四十章 晓风残月","id":"6062439"},{"title":"第四十一章 少女猫（上）","id":"6062440"},{"title":"第四十二章 少女猫（下）","id":"6062441"},{"title":"第四十三章 午夜微博","id":"6062442"},{"title":"第四十四章 引尸","id":"6062443"},{"title":"第四十五章 闺蜜","id":"6062444"},{"title":"第四十六章 闺蜜的杀机","id":"6062445"},{"title":"第四十七章 恶有恶报","id":"6062446"},{"title":"第四十八章 奇怪的乞丐","id":"6062447"},{"title":"第四十九章 阴阳情未了","id":"6062448"},{"title":"第五十章 玉柒的占卜（上）","id":"6062449"},{"title":"第五十一章 玉柒的占卜（下）","id":"6062450"},{"title":"第五十二章 可疑的身边人（上）","id":"6062451"},{"title":"第五十三章 可疑的身边人（下）","id":"6062452"},{"title":"第五十四章 拜师（上）","id":"6062453"},{"title":"第五十五章 拜师（下）","id":"6062454"},{"title":"第五十六章 鬼来电（上）","id":"6062455"},{"title":"第五十七章 鬼来电（下）","id":"6062456"},{"title":"第五十八章 坠楼之谜","id":"6062457"},{"title":"第五十九章 五眼六通（上）","id":"6062458"},{"title":"第六十章 五眼六通（下） 祝思思跟蘑菇生日快乐~！么么哒~！","id":"6062459"},{"title":"第六十一章 楚歌死亡真相","id":"6062460"},{"title":"第六十二章 绑错的姻缘线（上）","id":"6062461"},{"title":"第六十三章 绑错的姻缘线（下）","id":"6062462"},{"title":"第六十四章 母子情","id":"6062463"},{"title":"第六十五章 各怀鬼胎","id":"6062464"},{"title":"第六十六章 恐怖旅馆（上）","id":"6062465"},{"title":"第六十七章 恐怖旅馆（中）","id":"6062466"},{"title":"第六十八章 恐怖旅馆（下）","id":"6062467"},{"title":"第六十九章 闫至阳跟狗不得入内","id":"6062468"},{"title":"第七十章 鬼宾馆（上）","id":"6062469"},{"title":"第七十一章 鬼宾馆（中）","id":"6062470"},{"title":"第七十二章 鬼宾馆（下）","id":"6062471"},{"title":"第七十三章 诡梦","id":"6062472"},{"title":"第七十四章 宾馆秘闻","id":"6062473"},{"title":"第七十五章 行踪可疑的宁思","id":"6062474"},{"title":"第七十六章 愚昧的对手","id":"6062475"},{"title":"第七十七章 荒废敬老院里的神秘老人","id":"6062476"},{"title":"第七十八章 暗夜杀机（上）","id":"6062477"},{"title":"第七十九章 暗夜杀机（中）","id":"6062478"},{"title":"第八十章 暗夜杀机（下）","id":"6062479"},{"title":"第八十一章 闫至阳的私生子？","id":"6062480"},{"title":"第八十二章 被关石墓","id":"6062481"},{"title":"第八十三章 黑衣人","id":"6062482"},{"title":"第八十四章 宁思失踪（上）","id":"6062483"},{"title":"第八十五章 宁思失踪（中）","id":"6062484"},{"title":"第八十六章 宁思失踪（下）","id":"6062485"},{"title":"第八十七章 小寒的身份","id":"6062486"},{"title":"第八十八章 情深如斯","id":"6062487"},{"title":"第八十九章 赵无眠","id":"6062488"},{"title":"第九十章 情恨","id":"6062489"},{"title":"第九十一章 身体里长针的男孩（上）","id":"6062490"},{"title":"第九十二章 身体里长针的男孩（下）","id":"6062491"},{"title":"第九十三章 玉家老宅","id":"6062492"},{"title":"第九十四章 狭路相逢","id":"6062493"},{"title":"第九十五章 怪病","id":"6062494"},{"title":"第九十六章 倒影透析术（上）","id":"6062495"},{"title":"第九十七章 倒影透析术（中）","id":"6062496"},{"title":"第九十八章 倒影透析术（下）","id":"6062497"},{"title":"第九十九章 隐藏的敌人","id":"6062498"},{"title":"第一百章 前世今生之苻坚慕容冲（上）","id":"6062499"},{"title":"第一百零一章 前世今生之苻坚慕容冲（下）","id":"6062500"},{"title":"第一百零二章 脱离幻境","id":"6062501"},{"title":"第一百零三章 神秘少年","id":"6062502"},{"title":"第一百零四章 书中的灵魂（上）","id":"6062503"},{"title":"第一百零五章 书中的灵魂（下）","id":"6062504"},{"title":"第一百零六章 厉小璐（上）","id":"6062505"},{"title":"第一百零七章 厉小璐（下）","id":"6062506"},{"title":"第一百零八章 古怪的老宅","id":"6062507"},{"title":"第一百零九章 莫名低语","id":"6062508"},{"title":"第一百一十章 五鬼驮运（上）","id":"6062509"},{"title":"第一百一十一章 五鬼驮运（中）","id":"6062510"},{"title":"第一百一十二章 五鬼驮运（下）","id":"6062511"},{"title":"第一百一十三章 善恶到头终有报（上）","id":"6062512"},{"title":"第一百一十四章 善恶到头终有报（中）","id":"6062513"},{"title":"第一百一十五章 善恶到头终有报（下）","id":"6062514"},{"title":"第一百一十六章 会说话的干脆面君","id":"6062515"},{"title":"第一百一十七章 为爱建造的鬼住宅（上）","id":"6062516"},{"title":"第一百一十八章 为爱建造的鬼住宅（中）","id":"6062517"},{"title":"第一百一十九章 为爱建造的鬼住宅（下）","id":"6062518"},{"title":"第一百二十章 出乎意料的人（上） 感谢谢星河玉佩打赏~！么么哒","id":"6062519"},{"title":"第一百二十一章 出乎意料之外的人（中）","id":"6062520"},{"title":"第一百二十二章 出乎意料之外的人（下）","id":"6062521"},{"title":"第一百二十三章 蛇窟求生（上）","id":"6062522"},{"title":"第一百二十四章 蛇窟求生（下）","id":"6062523"},{"title":"第一百二十五章 变脸","id":"6062524"},{"title":"第一百二十六章 真正的宁思（上）","id":"6062525"},{"title":"第一百二十七章 真正的宁思（下）","id":"6062526"},{"title":"第一百二十八章 复制体","id":"6062527"},{"title":"第一百二十九章 人皮灯罩（上）","id":"6062528"},{"title":"第一百三十章 人皮灯罩（中）","id":"6062529"},{"title":"第一百三十一章 人皮灯罩（下）","id":"6062530"},{"title":"第一百三十二章 剥皮屋","id":"6062531"},{"title":"第一百三十三章 凶恶鬼蚁（上）","id":"6062532"},{"title":"第一百三十四章 凶恶鬼蚁（中）","id":"6062533"},{"title":"第一百三十五章 凶恶鬼蚁（下）","id":"6062534"},{"title":"第一百三十六章 村子的诅咒（上）","id":"6062535"},{"title":"第一百三十七章 村子的诅咒（中）","id":"6062536"},{"title":"第一百三十八章 村子的诅咒（下）","id":"6062537"},{"title":"第一百三十九章 怪异村庄","id":"6062538"},{"title":"第一百四十章 情愫","id":"6062539"},{"title":"第一百四十一章 诛邪（上）","id":"6062540"},{"title":"第一百四十二章 诛邪（下）","id":"6062541"},{"title":"第一百四十三章 神秘讯息","id":"6062542"},{"title":"第一百四十四章 古楼白裙（上）","id":"6062543"},{"title":"第一百四十五章 古楼白裙（中）","id":"6062544"},{"title":"第一百四十六章 古楼白裙（下）","id":"6062545"},{"title":"第一百四十七章 前世噩梦","id":"6062546"},{"title":"第一百四十八章 蛊婆复仇","id":"6062547"},{"title":"第一百四十九章 幻鬼","id":"6062548"},{"title":"第一百五十章 猫肉火锅（上）","id":"6062549"},{"title":"第一百五十一章 猫肉火锅（下）","id":"6062550"},{"title":"第一百五十二章 屠村（上）","id":"6062551"},{"title":"第一百五十三章 屠村（下）","id":"6062552"},{"title":"第一百五十四章 前仇旧怨（上）","id":"6062553"},{"title":"第一百五十五章 前仇旧怨（中）","id":"6062554"},{"title":"第一百五十六章 前仇旧怨（下）","id":"6062555"},{"title":"第一百五十七章 杀人玉佛（上）","id":"6062556"},{"title":"第一百五十八章 杀人玉佛（中）","id":"6062557"},{"title":"第一百五十九章 杀人玉佛（下）","id":"6062558"},{"title":"第一百六十章 厉笙歌的秘密！","id":"6062559"},{"title":"第一百六十一章 杀手之王","id":"6062560"},{"title":"第一百六十二章 谢星河的目的","id":"6062561"},{"title":"第一百六十三章 逗逼文艺","id":"6062562"},{"title":"第一百六十四章 新娘的诅咒（上）","id":"6062563"},{"title":"第一百六十五章 新娘的诅咒（中）","id":"6062564"},{"title":"第一百六十六章 新娘的诅咒（下）","id":"6062565"},{"title":"第一百六十七章 年坑（上）","id":"6062566"},{"title":"第一百六十八章 年坑（下）","id":"6062567"},{"title":"第一百六十九章 银元杀人","id":"6062568"},{"title":"第一百七十章 神秘的陆家人","id":"6062569"},{"title":"第一百七十一章 暗室人偶","id":"6062570"},{"title":"第一百七十二章 陆行云的身世","id":"6062571"},{"title":"第一百七十三章 云昔","id":"6062572"},{"title":"第一百七十四章 陆家的秘密（上）","id":"6062573"},{"title":"第一百七十五章 陆家的秘密（中）","id":"6062574"},{"title":"第一百七十六章 陆家的秘密（下）","id":"6062575"},{"title":"第一百七十七章 变脸人（上）","id":"6062576"},{"title":"第一百七十八章 变脸人（中）","id":"6062577"},{"title":"第一百七十九章 变脸人（下）","id":"6062578"},{"title":"第一百八十章 同心结","id":"6062579"},{"title":"第一百八十一章 永恒魔咒","id":"6062580"},{"title":"第一百八十二章 古怪的石室","id":"6062581"},{"title":"第一百八十三章 僵尸道士（上）","id":"6062582"},{"title":"第一百八十四章 僵尸道士（中）","id":"6062583"},{"title":"第一百八十五章 僵尸道士（下）","id":"6062584"},{"title":"第一百八十六章 丢失的柱础","id":"6062585"},{"title":"第一百八十七章 碎剑之石（上）","id":"6062586"},{"title":"第一百八十八章 碎剑之石（中）","id":"6062587"},{"title":"第一百八十九章 碎剑之石（下）","id":"6062588"},{"title":"第一百九十章 装逼扇","id":"6062589"},{"title":"第一百九十一章 傲娇的作家","id":"6062590"},{"title":"第一百九十二章 失踪的约会","id":"6062591"},{"title":"第一百九十三章 冥婚中介","id":"6062592"},{"title":"第一百九十四章 男神的致命约会","id":"6062593"},{"title":"第一百九十五章 征冥婚","id":"6062594"},{"title":"第一百九十六章 明星鬼老婆（上）","id":"6062595"},{"title":"第一百九十七章 明星鬼老婆（中）","id":"6062596"},{"title":"第一百九十八章 明星鬼老婆（下）","id":"6062597"},{"title":"第一百九十九章 美瞳","id":"6062598"},{"title":"第二百章 意乱情迷","id":"6062599"},{"title":"第二百零一章 古宅到底是什么","id":"6062600"},{"title":"第二百零二章 鬼青楼","id":"6062601"},{"title":"第二百零三章 阴阳乱序，人间大劫（上）","id":"6062602"},{"title":"第二百零四章 阴阳乱序，人间大劫（下）","id":"6062603"},{"title":"第二百零五章 内疚","id":"6062604"},{"title":"第二百零六章 毒药（上）","id":"6062605"},{"title":"第二百零七章 毒药（下）","id":"6062606"},{"title":"第二百零八章 鬼店鬼歌谣","id":"6062607"},{"title":"第二百零九章 宝贝对不起","id":"6062608"},{"title":"第二百一十章 千岁塚（上）","id":"6062609"},{"title":"第二百一十一章 千岁塚（中）","id":"6062610"},{"title":"第二百一十二章 千岁塚（下）","id":"6062611"},{"title":"第二百一十三章 何家老屋的神秘电话","id":"6062612"},{"title":"第二百一十四章 血迹斑斑的嫁衣","id":"6062613"},{"title":"第二百一十五章 死亡村","id":"6062614"},{"title":"第二百一十六章 相爱相杀（上）","id":"6062615"},{"title":"第二百一十七章 相爱相杀（中）","id":"6062616"},{"title":"第二百一十八章 相爱相杀（下）","id":"6062617"},{"title":"第二百一十九章 既见君子，云胡不喜","id":"6062618"},{"title":"第二百二十章 百年毒局（上）","id":"6062619"},{"title":"第二百二十一章 百年毒局（中）","id":"6062620"},{"title":"第二百二十二章 百年毒局（下）","id":"6062621"},{"title":"第二百二十三章 神秘的余落","id":"6062622"},{"title":"第二百二十四章 石磨街的传说","id":"6062623"},{"title":"第二百二十五章 老邮差","id":"6062624"},{"title":"第二百二十六章 邮戳救命","id":"6062625"},{"title":"第二百二十七章 将军镇的真相（上）","id":"6062626"},{"title":"第二百二十八章 将军镇的真相（中）","id":"6062627"},{"title":"第二百二十九章 将军镇的真相（下）","id":"6062628"},{"title":"第二百三十章 出乎意料的背叛","id":"6062629"},{"title":"第二百三十一章 鬼镇覆灭（上）","id":"6062630"},{"title":"第二百三十二章 鬼镇覆灭（下）","id":"6062631"},{"title":"第二百三十三章 荒岛女尸（上）","id":"6062632"},{"title":"第二百三十四章 荒岛女尸（下）","id":"6062633"},{"title":"第二百三十五章 真相的片段","id":"6062634"},{"title":"第二百三十六章 意外之伤","id":"6062635"},{"title":"第二百三十七章 五帝钱","id":"6062636"},{"title":"第二百三十八章 午夜红色轿子","id":"6062637"},{"title":"第二百三十九章 上鬼花轿（上）","id":"6062638"},{"title":"第二百四十章 上鬼花轿（下）","id":"6062639"},{"title":"第二百四十一章 嫌犯","id":"6062640"},{"title":"第二百四十二章 恐怖梦境","id":"6062641"},{"title":"第二百四十三章 死亡之虫","id":"6062642"},{"title":"第二百四十四章 四面楚歌","id":"6062643"},{"title":"第二百四十五章 重逢","id":"6062644"},{"title":"第二百四十六章 心魔（上）","id":"6062645"},{"title":"第二百四十七章 心魔（下）","id":"6062646"},{"title":"第二百四十八章 迷惑人心的游戏","id":"6062647"},{"title":"第二百四十九章 恐怖旅馆","id":"6062648"},{"title":"第二百五十章 少年战神（上）","id":"6062649"},{"title":"第二百五十一章 少年战神（下）","id":"6062650"},{"title":"第二百五十二章 井盖下的冤魂","id":"6062651"},{"title":"第二百五十三章 技术宅的报复","id":"6062652"},{"title":"第二百五十四章 三个人的电影","id":"6062653"},{"title":"第二百五十五章 求药","id":"6062654"},{"title":"第二百五十六章 山村怪嚎（上）","id":"6062655"},{"title":"第二百五十七章 山村怪嚎（中）","id":"6062656"},{"title":"第二百五十八章 山村怪嚎（下）","id":"6062657"},{"title":"第二百五十九章 故人（上）","id":"6062658"},{"title":"第二百六十章 故人（中）","id":"6062659"},{"title":"第二百六十一章 故人（下）","id":"6062660"},{"title":"第二百六十二章 深水龙潭","id":"6062661"},{"title":"第二百六十三章 人烛灯（上）","id":"6062662"},{"title":"第二百六十四章 人烛灯（下）","id":"6062663"},{"title":"第二百六十五章 又一次意外背叛","id":"6062664"},{"title":"第二百六十六章 狭路相逢","id":"6062665"},{"title":"第二百六十七章 玄天剑的下落","id":"6062666"},{"title":"第二百六十八章 铸剑世家","id":"6062667"},{"title":"第二百六十九章 凶剑出世（上）","id":"6062668"},{"title":"第二百七十章 凶剑出世（中）","id":"6062669"},{"title":"第二百七十一章 凶剑出世（下）","id":"6062670"},{"title":"第二百七十二章 空白绢帛","id":"6062671"},{"title":"第二百七十三章 温情的鬼魂（上）","id":"6062672"},{"title":"第二百七十四章 温情的鬼魂（中）","id":"6062673"},{"title":"第二百七十五章 温情的鬼魂（下）","id":"6062674"},{"title":"第二百七十六章 阴阳一线间","id":"6062675"},{"title":"第二百七十七章 水下王城（上）","id":"6062676"},{"title":"第二百七十八章 水下王城（中）","id":"6062677"},{"title":"第二百七十九章 水下王城（下）","id":"6062678"},{"title":"第二百八十章 忠奸难辨","id":"6062679"},{"title":"第二百八十一章 逼真的怨偶","id":"6062680"},{"title":"第二百八十二章 书剑情侠柳三变与皇帝的迷情","id":"6062681"},{"title":"第二百八十三章 娃娃的主人是男人","id":"6062682"},{"title":"第二百八十四章 娃娃化妆师","id":"6062683"},{"title":"第二百八十五章 炼魂术","id":"6062684"},{"title":"第二百八十六章 八卦罗盘","id":"6062685"},{"title":"第二百八十七章 赤瞳裂眶鬼","id":"6062686"},{"title":"第二百八十八章 淫魔俱乐部","id":"6062687"},{"title":"第二百八十九章 意外邂逅","id":"6062688"},{"title":"第二百九十章 神秘女杀手","id":"6062689"},{"title":"第二百九十一章 淫魔宿主（上） 感谢猫猫打赏玉佩~！么么哒~！","id":"6062690"},{"title":"第二百九十二章 淫魔宿主（中）","id":"6062691"},{"title":"第二百九十三章 淫魔宿主（下）","id":"6062692"},{"title":"第二百九十四章 火龙烈焰（上）","id":"6062693"},{"title":"第二百九十五章 火龙烈焰（下）","id":"6062694"},{"title":"第二百九十六章 华藏教门（上）","id":"6062695"},{"title":"第二百九十七章 华藏教门（中）","id":"6062697"},{"title":"第二百九十八章 华藏教门（下）","id":"6062698"},{"title":"第二百九十九章 奇怪的西点餐厅","id":"6062699"},{"title":"第三百章 古怪的巷子","id":"6062700"},{"title":"第三百零一章 色魔教主","id":"6062701"},{"title":"第三百零二章 念瑶（上）","id":"6062702"},{"title":"第三百零三章 念瑶（中）","id":"6062703"},{"title":"第三百零四章 念瑶（下）","id":"6062704"},{"title":"第三百零五章 人偶","id":"6062705"},{"title":"第三百零六章 灵异游戏（上）","id":"6062706"},{"title":"第三百零七章 灵异游戏（中）","id":"6062707"},{"title":"第三百零八章 灵异游戏（下）","id":"6062708"},{"title":"第三百零九章 古楼惊魂夜（上）","id":"6062709"},{"title":"第三百一十章 古楼惊魂夜（中）","id":"6062710"},{"title":"第三百一十一章 古楼惊魂夜（下）","id":"6062711"},{"title":"第三百一十二章 死人复活（上）","id":"6062712"},{"title":"第三百一十三章 死人复活（中）","id":"6062713"},{"title":"第三百一十四章 死人复活（下）","id":"6062714"},{"title":"第三百一十五章 诡计捉凶","id":"6062715"},{"title":"第三百一十六章 猫灵（上）","id":"6062716"},{"title":"第三百一十七章 猫灵（下）","id":"6062717"},{"title":"第三百一十八章 吃人鱼塘（上）","id":"6062718"},{"title":"第三百一十九章 吃人鱼塘（中）","id":"6062719"},{"title":"第三百二十章 吃人鱼塘（下）","id":"6062720"},{"title":"第三百二十一章 山村老尸","id":"6062721"},{"title":"第三百二十二章 地窖碎尸","id":"6062722"},{"title":"第三百二十三章 猫尸","id":"6062723"},{"title":"第三百二十四章 异村（上）","id":"6062724"},{"title":"第三百二十四章 异村（中）","id":"6062725"},{"title":"第三百二十五章 异村（下）","id":"6062726"},{"title":"第三百二十六章 毒","id":"6062727"},{"title":"第三百二十七章 意想不到的身份","id":"6062728"},{"title":"第三百二十八章 至阳剑","id":"6062729"},{"title":"第三百二十九章 杀人电梯","id":"6062730"},{"title":"第三百三十章 电梯里的异度空间（上）","id":"6062731"},{"title":"第三百三十一章 电梯里的异度空间（中）","id":"6062732"},{"title":"第三百三十二章 电梯里的异度空间（下）","id":"6062733"},{"title":"第三百三十三章 镜花水月的幻境","id":"6062734"},{"title":"第三百三十四章 重伤","id":"6062735"},{"title":"第三百三十五章 近在眼前","id":"6062736"},{"title":"第三百三十六章 玄天剑","id":"6062737"},{"title":"第三百三十七章 恶灵由心（上）","id":"6062738"},{"title":"第三百三十八章 恶灵由心（下）","id":"6062739"},{"title":"第三百三十九章 别有用心","id":"6062740"},{"title":"第三百四十章 降头墙（上）","id":"6062741"},{"title":"第三百四十一章 降头墙（中）","id":"6062742"},{"title":"第三百四十二章 降头墙（下）","id":"6062743"},{"title":"第三百四十三章 再见装逼扇","id":"6062744"},{"title":"第三百四十四章 上穷碧落下黄泉，冲冠一怒（上）","id":"6062745"},{"title":"第三百四十五章 上穷碧落下黄泉，冲冠一怒（下）","id":"6062746"},{"title":"第三百四十六章 回眸","id":"6062747"},{"title":"第三百四十七章 为你逆天有何不可","id":"6062748"},{"title":"第三百四十八章 玄天剑的归处","id":"6062749"},{"title":"第三百四十九章 玄天剑认主","id":"6062750"},{"title":"第三百五十章 六十年的怪胎","id":"6062751"},{"title":"第三百五十一章 诡异的标本","id":"6062752"},{"title":"第三百五十二章 清朝格格墓","id":"6062753"},{"title":"第三百五十三章 守墓人的秘密","id":"6062754"},{"title":"第三百五十四章 另一个人","id":"6062755"},{"title":"第三百五十五章 古墓里的秘密","id":"6062756"},{"title":"第三百五十六章 黑暗内幕（上）","id":"6062757"},{"title":"第三百五十七章 黑暗内幕（下）","id":"6062758"},{"title":"第三百五十八章 逃出生天","id":"6062759"},{"title":"第三百五十九章 人生如戏，全靠演技","id":"6062760"},{"title":"第三百六十章 古墓石雕像","id":"6062761"},{"title":"第三百六十一章 他乡遇故人","id":"6062762"},{"title":"第三百六十二章 金老头","id":"6062763"},{"title":"第三百六十三章 千年鬼","id":"6062764"},{"title":"第三百六十四章 守阴墓","id":"6062765"},{"title":"第三百六十五章 墓中密","id":"6062766"},{"title":"第三百六十六章 恐怖的眼睛","id":"6062767"},{"title":"第三百六十七章 异地重逢","id":"6062768"},{"title":"第三百六十八章 帅的不明显的道长","id":"6062769"},{"title":"第三百六十九章 老道的过去","id":"6062770"},{"title":"第三百七十章 乡村起尸","id":"6062771"},{"title":"第三百七十一章 禁术窥秘（上）","id":"6062772"},{"title":"第三百七十二章 禁术窥秘（中）","id":"6062773"},{"title":"第三百七十三章 禁术窥秘（下）","id":"6062774"},{"title":"第三百七十四章 闫至阳的秘密","id":"6062775"},{"title":"第三百七十五章 蛇人","id":"6062776"},{"title":"第三百七十六章 怪异的鱼塘","id":"6062777"},{"title":"第三百七十七章 鬼崽石人","id":"6062778"},{"title":"第三百七十八章 续魂阵","id":"6062779"},{"title":"第三百七十九章 反其道而行之的邪术","id":"6062780"},{"title":"第三百八十章 诡异的年轻夫妻","id":"6062781"},{"title":"第三百八十一章 出乎意料的身份","id":"6062782"},{"title":"第三百八十二章 红窗户","id":"6062783"},{"title":"第三百八十三章 惨梦","id":"6062784"},{"title":"第三百八十四章 人偶的喻示","id":"6062785"},{"title":"第三百八十五章 纸人技","id":"6062786"},{"title":"第三百八十六章 衣冠禽兽","id":"6062787"},{"title":"第三百八十七章 人头梨，婊子哭","id":"6062788"},{"title":"第三百八十八章 滴水观音","id":"6062789"},{"title":"第三百八十九章 明星降头术","id":"6062790"},{"title":"第三百九十章 花降","id":"6062791"},{"title":"第三百九十一章 飞头降","id":"6062792"},{"title":"第三百九十二章 神秘的蛊婆","id":"6062793"},{"title":"第三百九十三章 设局抓凶","id":"6062794"},{"title":"第三百九十四章 狭路相逢","id":"6062795"},{"title":"第三百九十五章 绝杀","id":"6062796"},{"title":"第三百九十六章 幕后黑手","id":"6062797"},{"title":"第三百九十七章 再赴山东","id":"6062798"},{"title":"第三百九十八章 五鬼运财","id":"6062799"},{"title":"第三百九十九章 神秘暗杀（上）","id":"6062800"},{"title":"第四百章 神秘暗杀（下）","id":"6062801"},{"title":"第四百零一章 怪异的陆家人","id":"6062802"},{"title":"第四百零二章 妖仙鬼宅","id":"6062803"},{"title":"第四百零三章 突围","id":"6062804"},{"title":"第四百零四章 脱身","id":"6062805"},{"title":"第四百零五章 暗访凶宅","id":"6062806"},{"title":"第四百零六章 迷失在幻境","id":"6062807"},{"title":"第四百零七章 兴师问罪（上）","id":"6062808"},{"title":"第四百零八章 兴师问罪（下）","id":"6062809"},{"title":"第四百零九章 守株待兔","id":"6062810"},{"title":"第四百一十章 陆青川之死","id":"6062811"},{"title":"第四百一十一章 疑窦丛生","id":"6062812"},{"title":"第四百一十二章 恐怖的死法","id":"6062813"},{"title":"第四百一十三章 诡异的脸孔","id":"6062814"},{"title":"第四百一十四章 神秘女友","id":"6062815"},{"title":"第四百一十五章 丑陋真相","id":"6062816"},{"title":"第四百一十六章 鬼火焚身（上）","id":"6062817"},{"title":"第四百一十七章 鬼火焚身（中）","id":"6062818"},{"title":"第四百一十八章 鬼火焚身（下）","id":"6062819"},{"title":"第四百一十九章 鬼事四起（上）","id":"6062820"},{"title":"第四百二十章 鬼事四起（中）","id":"6062821"},{"title":"第四百二十一章 鬼事四起（下）","id":"6062822"},{"title":"第四百二十二章 禅度","id":"6062823"},{"title":"第四百二十三章 困城（上）","id":"6062824"},{"title":"第四百二十四章 困城（中）","id":"6062825"},{"title":"第四百二十五章 困城（下）","id":"6062826"},{"title":"第四百二十六章 鬼蜮真相（上）","id":"6062827"},{"title":"第四百二十七章 鬼蜮真相（中）","id":"6062828"},{"title":"第四百二十八章 鬼蜮的真相（下）","id":"6062829"},{"title":"第四百二十九章 意外的人","id":"6062830"},{"title":"第四百三十章 祖卉之死","id":"6062831"},{"title":"第四百三十一章 跌入陷阱","id":"6062832"},{"title":"第四百三十二章 困境","id":"6062833"},{"title":"第四百三十三章 对决（上）","id":"6062834"},{"title":"第四百三十四章 对决（中）","id":"6062835"},{"title":"第四百三十五章 对决（下）","id":"6062836"},{"title":"第三百三十六章 别离（上）","id":"6062837"},{"title":"第四百三十七章 别离（中）","id":"6062838"},{"title":"第四百三十八章 别离（下）","id":"6062839"},{"title":"第四百三十九章 再度到来的危机（上）","id":"6062840"},{"title":"第四百四十章 再度到来的危机（中）","id":"6062841"},{"title":"第四百四十一章 再度到来的危机（下）","id":"6062842"},{"title":"第四百四十二章 迷香幻境","id":"6062843"},{"title":"第四百四十三章 出乎意料的反转","id":"6062844"},{"title":"第四百四十四章 爱的人已反目（上）","id":"6062845"},{"title":"第四百四十五章 爱的人已反目（中）","id":"6062846"},{"title":"第四百四十六章 爱的人已反目（下）","id":"6062847"},{"title":"第四百四十七章 游园惊梦（上）","id":"6062848"},{"title":"第四百四十八章 游园惊梦（中）","id":"6062849"},{"title":"第四百四十九章 游园惊梦（下）","id":"6062850"},{"title":"第四百五十章 观灵术","id":"6062851"},{"title":"第四百五十一章 阴谋","id":"6062852"},{"title":"第四百五十二章 归来","id":"6062853"},{"title":"第四百五十三章 陷害（上）","id":"6062854"},{"title":"第四百五十四章 陷害（中）","id":"6062855"},{"title":"第四百五十五章 陷害（下）","id":"6062856"},{"title":"第四百五十六章 锄奸(上 )","id":"6062857"},{"title":"第四百五十七章 锄奸（下）","id":"6062858"},{"title":"第四百五十八章 厉家的秘密（上）","id":"6062859"},{"title":"第四百五十九章 厉家的秘密（中）","id":"6062860"},{"title":"第四百六十章 厉家的秘密（下）","id":"6062861"},{"title":"第四百六十一章 七爷来访","id":"6062862"},{"title":"第四百六十二章 宣吉阁","id":"6062863"},{"title":"第四百六十三章 怪梦","id":"6062864"},{"title":"第四百六十四章 困局","id":"6062865"},{"title":"第四百六十五章 死局（上）","id":"6062866"},{"title":"第四百六十六章 死局（中）","id":"6062867"},{"title":"第四百六十七章 死局（下）","id":"6062868"},{"title":"第四百六十八章 玉碎（上）","id":"6062869"},{"title":"第四百六十九章 玉碎（下）","id":"6062870"},{"title":"第四百七十章 恐怖的厉家","id":"6062871"},{"title":"第四百七十一章 谋杀","id":"6062872"},{"title":"第四百七十二章 内乱（上）","id":"6062873"},{"title":"第四百七十三章 内乱（下）","id":"6062874"},{"title":"第四百七十四章 宿命石（上）","id":"6062875"},{"title":"第四百七十五章 宿命石（中）","id":"6062876"},{"title":"第四百七十六章 宿命石（下）","id":"6062877"},{"title":"第四百七十七章 惨梦","id":"6062878"},{"title":"第四百七十八章 恩仇泯（上）","id":"6076263"},{"title":"第四百七十九章 恩仇泯（中）","id":"6077168"},{"title":"第四百八十章 恩仇泯（下）","id":"6083296"},{"title":"第四百八十一章 决裂（上）","id":"6088389"},{"title":"第四百八十二章 决裂（中）","id":"6089106"},{"title":"第四百八十三章 决裂（下）","id":"6095342"},{"title":"第四百八十四章 大结局","id":"6096036"}]