[{"title":"五行山下","id":"2377317"},{"title":"第一章","id":"2377319"},{"title":"第二章","id":"2377322"},{"title":"第三章","id":"2377324"},{"title":"第四章","id":"2377326"},{"title":"第五章","id":"2377328"},{"title":"第六章","id":"2377332"},{"title":"第七章","id":"2377333"},{"title":"第八章","id":"2377335"},{"title":"第九章","id":"2377338"},{"title":"第十章","id":"2377341"},{"title":"第十一章","id":"2377343"},{"title":"第十二章","id":"2377345"},{"title":"第十三章","id":"2377347"},{"title":"第十四章","id":"2377349"},{"title":"第十五章","id":"2377350"},{"title":"第十六章","id":"2377352"},{"title":"第十七章","id":"2377354"},{"title":"第十八章","id":"2377357"},{"title":"第十九章","id":"2377359"},{"title":"第二十章","id":"2377361"},{"title":"第二十一章","id":"2377363"},{"title":"第二十二章","id":"2377365"},{"title":"第二十三章","id":"2377367"},{"title":"第二十四章","id":"2377369"},{"title":"第二十五章","id":"2377371"},{"title":"第二十六章","id":"2377373"},{"title":"第二十七章","id":"2377376"},{"title":"第二十八章","id":"2377378"},{"title":"第二十九章","id":"2377380"},{"title":"第三十章","id":"2377382"},{"title":"第三十一章","id":"2377384"},{"title":"第三十二章","id":"2377385"},{"title":"第三十三章","id":"2377387"},{"title":"第三十四章","id":"2377389"},{"title":"第三十五章","id":"2377391"},{"title":"第三十六章","id":"2377393"},{"title":"第三十七章","id":"2377395"},{"title":"第三十八章","id":"2377397"},{"title":"第三十九章","id":"2377400"},{"title":"第四十章","id":"2377402"},{"title":"第四十一章","id":"2377404"},{"title":"第四十二章","id":"2377406"},{"title":"第四十三章","id":"2377409"},{"title":"第四十四章(求推荐票)","id":"2377411"},{"title":"第四十五章（求推荐！）","id":"2377413"},{"title":"第四十六章（求推荐票）","id":"2377415"},{"title":"第四十七章（狂求推荐票）","id":"2377417"},{"title":"第四十八章（强烈求推荐票）","id":"2377419"},{"title":"第四十九章(求推荐票)","id":"2377421"},{"title":"第五十章(求推荐票)","id":"2377423"},{"title":"第五十一章（求推荐票）","id":"2377425"},{"title":"第五十二章（大章求推荐）","id":"2377428"},{"title":"第五十三章（求推荐）","id":"2377430"},{"title":"第五十四章(晚上加更求推荐票)","id":"2377431"},{"title":"第五十五章（晚上加更求推荐票）","id":"2377433"},{"title":"第五十六章（加更求推荐票啊）","id":"2377435"},{"title":"第五十七章（求推荐票）","id":"2377437"},{"title":"第五十八章（推荐票怎么少了）","id":"2377440"},{"title":"第五十九章（求推荐票啊）","id":"2377442"},{"title":"第六十章（求推荐票啊啊啊啊）","id":"2377444"},{"title":"第六十一章（我要推荐票啊）","id":"2377446"},{"title":"第六十二章（求推荐票啊！）","id":"2377448"},{"title":"第六十三章（求推荐票啊！）","id":"2377449"},{"title":"第六十四章（求推荐票啊！）","id":"2377451"},{"title":"第六十五章（推荐票怎么少了）","id":"2377453"},{"title":"第六十六章（推荐票啊推荐票）","id":"2377455"},{"title":"第六十七章（求推荐求推荐）","id":"2377457"},{"title":"第六十八章（求推荐票啊）","id":"2377460"},{"title":"第六十九章（求票票啊）","id":"2377463"},{"title":"第七十章（求推荐票）","id":"2377466"},{"title":"第七十一章（推荐票啊）","id":"2377468"},{"title":"第七十二章（求推荐票……）","id":"2377469"},{"title":"第七十三章（求推荐票……）","id":"2377471"},{"title":"第七十四章（推荐票）","id":"2377473"},{"title":"第七十五章（推荐票啊推荐票）","id":"2377475"},{"title":"第七十六章（二更求推荐票）","id":"2377477"},{"title":"第七十七章（今天三更求推荐票）","id":"2377478"},{"title":"第七十八章：伏击","id":"2377479"},{"title":"第七十九章：队伍","id":"2377480"},{"title":"第八十章：内部矛盾","id":"2377482"},{"title":"第八十一章：胁迫式表决","id":"2377484"},{"title":"第八十二章：白猿的彷徨","id":"2377486"},{"title":"第八十三章：小狐妖的愿望","id":"2377488"},{"title":"第八十四章：短嘴的消息","id":"2377490"},{"title":"第八十五章：豺狼的毒计","id":"2377493"},{"title":"第八十六章：这是妖","id":"2377495"},{"title":"第八十七章：恶龙城","id":"2377496"},{"title":"第八十八章：金精","id":"2377499"},{"title":"第八十九章：不速之客","id":"2377500"},{"title":"第九十章：醉","id":"2377502"},{"title":"第九十一章：恶蛟","id":"2377504"},{"title":"第九十二章：分歧","id":"2377506"},{"title":"第九十三章：松鼠精","id":"2377508"},{"title":"第九十四章：自荐","id":"2377510"},{"title":"第九十五章：你疯了吗","id":"2377512"},{"title":"九十六章：区区小计","id":"2377515"},{"title":"第九十七章：恶蛟搅局","id":"2377517"},{"title":"第九十八章：反","id":"2377518"},{"title":"第九十九章：绝境","id":"2377521"},{"title":"第一百章：破碎的梦","id":"2377522"},{"title":"第一百零一章：冰封","id":"2377524"},{"title":"第一百零二章：蛰伏","id":"2377526"},{"title":"第一百零三章：收编(修改)","id":"2377528"},{"title":"第一百零四章：铁腕","id":"2377530"},{"title":"第一百零五章：守住神智","id":"2377537"},{"title":"第一百零六章：使者","id":"2377539"},{"title":"第一百零七章：杀心","id":"2377541"},{"title":"第一百零八章：前夕","id":"2377543"},{"title":"第一百零九章：示弱","id":"2377546"},{"title":"第一百一十章：兵变","id":"2377549"},{"title":"第一百一十一章：围困","id":"2377551"},{"title":"第一百一十二章：真相","id":"2377552"},{"title":"第一百一十三章：屠戮","id":"2377556"},{"title":"第一百一十四章：别无选择","id":"2377557"},{"title":"第一百一十五章：战前","id":"2377560"},{"title":"第一百一十六章：第三方","id":"2377563"},{"title":"第一百一十七章：箭雨","id":"2377565"},{"title":"第一百一十八章：拥挤","id":"2377568"},{"title":"第一百一十八章：拒流阵","id":"2377572"},{"title":"第一百二十章：阵前戏言","id":"2377574"},{"title":"第一百二十一章：绝计","id":"2377576"},{"title":"第一百二十二章：袭营","id":"2377577"},{"title":"第一百二十三章：困兽","id":"2377579"},{"title":"第一百二十四章：厮杀","id":"2377581"},{"title":"第一百二十五章：反正我不是","id":"2377583"},{"title":"第一百二十六章：灵力索","id":"2377585"},{"title":"第一百二十七章：太乙金仙","id":"2377587"},{"title":"第一百二十八章：亏欠","id":"2377589"},{"title":"第一百二十九章：巨人","id":"2377591"},{"title":"第一百三十章：等待","id":"2377593"},{"title":"第一百三十一章：三尖两刃刀","id":"2377595"},{"title":"第一百三十二章：不该管","id":"2377597"},{"title":"第一百三十三章：毫无胜算","id":"2377600"},{"title":"第一百三十四章：逝者","id":"2377602"},{"title":"第一百三十五章：四只小妖","id":"2377604"},{"title":"第一百三十六章：心脏","id":"2377605"},{"title":"第一百三十七章：云域天港","id":"2377608"},{"title":"第一百三十八章：开价","id":"2377609"},{"title":"第一百三十九章：入谷","id":"2377611"},{"title":"第一百四十章：地府生灵","id":"2377613"},{"title":"第一百四十一章：安顿","id":"2377614"},{"title":"第一百四十二章：姻缘","id":"2377616"},{"title":"第一百四十三章：幽泉子","id":"2377619"},{"title":"第一百四十四章：执念","id":"2377621"},{"title":"第一百四十五章：来客","id":"2377623"},{"title":"第一百四十六章：迷阵","id":"2377625"},{"title":"第一百四十七章：师兄弟","id":"2377628"},{"title":"第一百四十八章：天道","id":"2377631"},{"title":"第一百四十九章：漩涡（弱弱求推荐票）","id":"2377633"},{"title":"第一百五十章：种子","id":"2377636"},{"title":"第一百五十一章：谈判","id":"2377638"},{"title":"第一百五十二章：不会亏","id":"2377640"},{"title":"第一百五十三章：复活之法","id":"2377642"},{"title":"第一百五十四章：重返花果山","id":"2377643"},{"title":"第一百五十五章：小草","id":"2377646"},{"title":"第一百五十六章：放任","id":"2377647"},{"title":"第一百五十七章：信函","id":"2377649"},{"title":"第一百五十八章：镇元子","id":"2377650"},{"title":"第一百五十九章：孤立无援","id":"2377653"},{"title":"第一百六十章：文字的力量","id":"2377655"},{"title":"第一百六十一章：监视","id":"2377657"},{"title":"第一百六十二章：善意","id":"2377659"},{"title":"第一百六十三章：薄命的不只红颜，还有忠良","id":"2377661"},{"title":"第一百六十四章：往事","id":"2377663"},{"title":"第一百六十五章：一个人的红尘","id":"2377664"},{"title":"【预告】关于上架！（必看）","id":"2377665"},{"title":"第一百六十六章：剑指南天门！","id":"2377666"},{"title":"第一百六十七章：求来生","id":"2377667"},{"title":"第一百六十八章：永世换永世","id":"2377669"},{"title":"第一百六十九章：虎归山","id":"2377671"},{"title":"第一百七十章：花果山来客","id":"2377674"},{"title":"第一百七十一章：龙女敖寸心","id":"2377676"},{"title":"第一百七十二章：建议","id":"2377678"},{"title":"第一百七十三章：花果山下","id":"2377680"},{"title":"第一百七十四章：慧泉","id":"2377682"},{"title":"第一百七十五章：东海事变","id":"2377683"},{"title":"第一百七十六章：东海龙王","id":"2377685"},{"title":"第一百七十七章：**烦","id":"2377687"},{"title":"第一百七十八章：宴","id":"2377689"},{"title":"第一百七十九章：言外之意","id":"2377693"},{"title":"第一百八十章：挽留","id":"2377694"},{"title":"第一百八十一章：坦白","id":"2377696"},{"title":"第一百八十二章 ：毅然决然","id":"2377698"},{"title":"第一百八十三章：圆筒状法器","id":"2377699"},{"title":"第一百八十四章：新时代的开端（二更求订阅）","id":"2377700"},{"title":"第一百八十五章：偶遇","id":"2377701"},{"title":"第一百八十六章：大本营","id":"2377702"},{"title":"第一百八十七章：考虑考虑","id":"2377704"},{"title":"第一百八十八章：好深一个坑","id":"2377706"},{"title":"第一百八十九章：悄然到访","id":"2377708"},{"title":"第一百九十章：潜入","id":"2377709"},{"title":"第一百九十一章：源自苦难的力量","id":"2377712"},{"title":"第一百九十二章：房间内外","id":"2377713"},{"title":"军令状~","id":"2377716"},{"title":"第一百九十三章：承诺","id":"2377719"},{"title":"第一百九十四章：漫游","id":"2377721"},{"title":"第一百九十五章：曝光（感谢JackieZXW）","id":"2377722"},{"title":"第一百九十六章：即将到来","id":"2377724"},{"title":"第一百九十七章：烧山","id":"2377726"},{"title":"第一百九十八章：俘虏","id":"2377727"},{"title":"第一百九十九章：招魂殿","id":"2377729"},{"title":"第两百章：不是人","id":"2377730"},{"title":"第两百零一章：突破？","id":"2377732"},{"title":"第两百零二章：心结松动","id":"2377734"},{"title":"第两百零三章：纠结","id":"2377736"},{"title":"第两百零四章：换","id":"2377737"},{"title":"第两百零五章：谈判","id":"2377740"},{"title":"第两百零六章：李靖的愤怒","id":"2377743"},{"title":"第两百零七章：夜袭","id":"2377744"},{"title":"第两百零八章：围杀","id":"2377746"},{"title":"第两百零九章：悔婚（加更）","id":"2377748"},{"title":"第两百一十章：拜别","id":"2377750"},{"title":"第两百一十二章：浑身法宝","id":"2377751"},{"title":"第两百一十二章：能不能打欠条？（加更）","id":"2377753"},{"title":"第两百一十三章：不能给","id":"2377755"},{"title":"第两百一十四章：值多少？（加更）","id":"2377758"},{"title":"第两百一十五章：怎么办？","id":"2377760"},{"title":"第两百一十六章：海啸","id":"2377764"},{"title":"第两百一十七章 ：博弈","id":"2377767"},{"title":"第两百一十八章：面子","id":"2377769"},{"title":"第两百一十九章：蓝色眼睛","id":"2377771"},{"title":"第两百二十章：久别重逢","id":"2377773"},{"title":"第两百二十一章：昏迷","id":"2377775"},{"title":"第两百二十二章：照料","id":"2377776"},{"title":"第两百二十三章：黑色冬季","id":"2377778"},{"title":"第两百二十四章：千万金精","id":"2377780"},{"title":"第两百二十五章：干儿子","id":"2377783"},{"title":"第两百二十六章：求个名字","id":"2377784"},{"title":"第两百二十七章：生了？","id":"2377786"},{"title":"第两百二十八章：严重的问题","id":"2377788"},{"title":"第两百二十九章：分蟠桃","id":"2377790"},{"title":"第两百三十章：两个都是给你的","id":"2377792"},{"title":"第两百三十一章：养得起的人","id":"2377794"},{"title":"第两百三十二章：不开心","id":"2377796"},{"title":"第两百三十三章：妖王的算盘","id":"2377798"},{"title":"第两百三十四章：大战将起","id":"2377801"},{"title":"第两百三十五章：完全压制","id":"2377802"},{"title":"第两百三十六章：先下手为强","id":"2377804"},{"title":"第两百三十七章：明朗","id":"2377806"},{"title":"第两百三十八章：记仇","id":"2377808"},{"title":"第两百三十九章：父子（加更）","id":"2377810"},{"title":"第两百四十章：路过","id":"2377813"},{"title":"第两百四十一章：撤与不撤","id":"2377814"},{"title":"第两百四十二章：抛杯为号","id":"2377817"},{"title":"第两百四十三章：内讧","id":"2377819"},{"title":"第两百四十四章：对峙","id":"2377821"},{"title":"第两百四十五章：两位天王的困境","id":"2377822"},{"title":"第两百四十六章：就此拜别","id":"2377824"},{"title":"第两百四十七章：旧疾复发","id":"2377826"},{"title":"第两百四十八章：找点事做","id":"2377829"},{"title":"第两百四十九章：天蓬的邀请","id":"2377831"},{"title":"第两百五十章：求见（加更）","id":"2377832"},{"title":"第两百五十一章：求蟠桃","id":"2377834"},{"title":"第两百五十二章：九头虫的困局（加更）","id":"2377836"},{"title":"第两百五十三章：门内门外","id":"2377839"},{"title":"第两百五十四章：互不信任（加更）","id":"2377841"},{"title":"第两百五十六章：两个蟠桃","id":"2377842"},{"title":"第两百五十六章：买断了？","id":"2377844"},{"title":"第两百五十七章：可有此事？","id":"2377846"},{"title":"第两百五十八章：承认与否","id":"2377848"},{"title":"第两百五十九章：达成协议","id":"2377850"},{"title":"第两百六十章：争吵","id":"2377852"},{"title":"第两百六十一章：复杂的关系（加更）","id":"2377854"},{"title":"第两百六十二章：变化","id":"2377856"},{"title":"第两百六十三章：不好惹的两个女人","id":"2377857"},{"title":"第两百六十四章：奇袭","id":"2377859"},{"title":"第两百六十五章：毒计","id":"2377860"},{"title":"第两百六十六章：废墟","id":"2377862"},{"title":"第两百六十七章：战报","id":"2377864"},{"title":"第两百六十八章：寻仇","id":"2377866"},{"title":"第两百六十九章：无处不在的战争","id":"2377869"},{"title":"第两百七十章：鱼饵","id":"2377871"},{"title":"第两百七十一章：犹豫","id":"2377873"},{"title":"第两百七十二章 ：闹剧","id":"2377875"},{"title":"第两百七十三章 ：宴会","id":"2377876"},{"title":"第两百七十四章 ：袭击开始","id":"2377878"},{"title":"第两百七十五章：天将战阵","id":"2377880"},{"title":"第两百七十六章：天将战阵（2）","id":"2377882"},{"title":"第两百七十七章：战舰内的战斗","id":"2377884"},{"title":"第两百七十八章：战斗状态","id":"2377887"},{"title":"第两百七十九章：妖王的特使","id":"2377889"},{"title":"第两百八十章 ：拒绝","id":"2377890"},{"title":"第两百八十一章 ：招揽","id":"2377892"},{"title":"第两百八十二章 ：商量","id":"2377896"},{"title":"第两百八十三章 ：委屈","id":"2377897"},{"title":"第两百八十四章 ：争吵","id":"2377899"},{"title":"第两百八十五章 ：想清楚","id":"2377900"},{"title":"第两百八十六章 ：忧虑","id":"2377901"},{"title":"第两百八十七章 ：意料之外","id":"2377905"},{"title":"第两百八十八章 ：拉赞助","id":"2377906"},{"title":"第两百八十九章 ：主攻方向","id":"2377909"},{"title":"第两百九十章 ：分兵","id":"2377911"},{"title":"第两百九十一章 ：捡便宜","id":"2377913"},{"title":"第两百九十二章 ：霜雨山血战","id":"2377915"},{"title":"第两百九十三章 ：所谓“站稳脚跟”","id":"2377917"},{"title":"第两百九十四章 ：带话","id":"2377919"},{"title":"第两百九十五章 ：抉择","id":"2377923"},{"title":"第两百九十六章 ：瘟水","id":"2377925"},{"title":"第两百九十七章 ：擦边球","id":"2377927"},{"title":"第两百九十八章 ：擦边球（2）","id":"2377930"},{"title":"第两百九十九章 ：发作","id":"2377932"},{"title":"第三百章 ：应对","id":"2377934"},{"title":"第三百零一章","id":"2377936"},{"title":"第三百零二章 ：先吃了","id":"2377937"},{"title":"第三百零三章 ：冲锋","id":"2377939"},{"title":"第三百零四章 ：噩耗","id":"2377940"},{"title":"第三百零五章 ：噩耗（2）","id":"2377942"},{"title":"第三百零六章 ：噩耗（3）","id":"2377945"},{"title":"第三百零七章 ：假支援","id":"2377947"},{"title":"第三百零八章 ：持久战？","id":"2377949"},{"title":"第三百零九章 ：天蓬的顾虑","id":"2377950"},{"title":"第三百一十章 ：进击的天港","id":"2377952"},{"title":"第三百一十一章 ：投靠我如何？","id":"2377955"},{"title":"第三百一十二章 ：对峙","id":"2377957"},{"title":"第三百一十三章 ：没有撞角的战舰","id":"2377958"},{"title":"第三百一十四章 ：对碾","id":"2377959"},{"title":"第三百一十五章 ：对碾（2）","id":"2377960"},{"title":"第三百一十六章 ：对碾（3）","id":"2377961"},{"title":"第三百一十七章 ：找援军","id":"2377962"},{"title":"第三百一十八章 ：释放李靖","id":"2377965"},{"title":"第三百一十九章 ：后继乏力的天河水军","id":"2377967"},{"title":"第三百二十章 ：谁也不见！","id":"2377971"},{"title":"第三百二十一章 ：无可奈何","id":"2377973"},{"title":"第三百二十二章 ：代价","id":"2377975"},{"title":"第三百二十三章 ：凌霄宝殿上","id":"2377976"},{"title":"第三百二十四章 ：如此甚好","id":"2377977"},{"title":"第三百二十五章 ：我叫雀儿？","id":"2377979"},{"title":"第三百二十六章 ：又吹牛","id":"2377981"},{"title":"第三百二十七章 ：“画地为牢”之策","id":"2377984"},{"title":"第三百二十八章 ：磨墨","id":"2377986"},{"title":"第三百二十九章 ：拟旨","id":"2377988"},{"title":"第三百三十章 ：命数","id":"2377989"},{"title":"第三百三十一章 ：圣旨到","id":"2377991"},{"title":"第三百三十二章 ：有人欢喜有人愁","id":"2377993"},{"title":"第三百三十三章 ：做梦都想宰了你","id":"2377995"},{"title":"第三百三十四章 ：卷 终","id":"2377997"},{"title":"第三百三十五章 ：天蓬要受审了？","id":"2377999"},{"title":"第三百三十六章 ：风铃是雀儿转世？","id":"2378001"},{"title":"第三百三十七章 ：下马威","id":"2378003"},{"title":"第三百三十八章 趁夜","id":"2378005"},{"title":"第三百三十九章 夜入鸿禧宫","id":"2378007"},{"title":"第三百四十章 ：乱测一通","id":"2378009"},{"title":"第三百四十一章 ：太上来要人","id":"2378011"},{"title":"第三百四十二章 ：意料不到的见面方式","id":"2378013"},{"title":"第三百四十三章 ：聊聊","id":"2378018"},{"title":"第三百四十四章 ：巨灵神来了","id":"2378020"},{"title":"第三百四十五章 ：挑天马","id":"2378023"},{"title":"第三百四十六章 ：悲痛欲绝的巨灵神","id":"2378025"},{"title":"第三百四十七章 ：御马监的用度","id":"2378027"},{"title":"第三百四十八章 ：婆罗僧揭谛","id":"2378029"},{"title":"第三百四十九章 ：天庭府库","id":"2378031"},{"title":"第三百五十章 ：命牌","id":"2378034"},{"title":"第三百五十一章 ：送来的帖子","id":"2378036"},{"title":"第三百五十二章 气息不对","id":"2378038"},{"title":"第三百五十三章 ：何为天道","id":"2378040"},{"title":"深夜公告","id":"2378042"},{"title":"第三百五十四章 灵丹","id":"2378044"},{"title":"第三百五十五章 ：到访","id":"2378045"},{"title":"第三百五十六张：剿妖的因由","id":"2378047"},{"title":"第三百五十七章 谈不拢","id":"2378049"},{"title":"第三百五十八章 蒂心要来了","id":"2378052"},{"title":"第三百五十九章 ：踏青","id":"2378054"},{"title":"第三百六十章：被识破","id":"2378055"},{"title":"第三百六十一章 揭谛亲至","id":"2378057"},{"title":"第三百六十二章 ：闭关","id":"2378060"},{"title":"第三百六十三章 ：升职了","id":"2378061"},{"title":"第三百六十四章 恭候","id":"2378063"},{"title":"第三百六十五章：瑶池","id":"2378066"},{"title":"第三百六十六章 翻脸了","id":"2378067"},{"title":"这是要坑了么……","id":"2378069"},{"title":"第三百六十七章 打草惊蛇","id":"2378071"},{"title":"第三百六十八章 ：无赖至极","id":"2378073"},{"title":"第三百六十九章 ：败露","id":"2378074"},{"title":"第三百七十章 ：分开处理","id":"2378077"},{"title":"第三百七十一章 ：兜率宫的庭院里","id":"2378078"},{"title":"第三百七十二章 ：刺痛","id":"2378081"},{"title":"第三百七十四章 ：先发制人","id":"2378083"},{"title":"第三百七十四章 抉择","id":"2378085"},{"title":"第三百七十五章：追逐","id":"2378087"},{"title":"第三百七十六章 ：深渊","id":"2378091"},{"title":"第三百七十七章 ：说错话了","id":"2378093"},{"title":"第三百七十八章 ：闯宫","id":"2378095"},{"title":"第三百七十九章 ：金刚琢","id":"2378097"},{"title":"第三百八十章：一门之隔","id":"2378100"},{"title":"第三百八十一章 ：被俘","id":"2378102"},{"title":"第三百八十二章 谈判","id":"2378103"},{"title":"第三百八十三章 ：心照不宣","id":"2378106"},{"title":"第三百八十四章 接下来……","id":"2378108"},{"title":"第三百八十五章 ：逃跑","id":"2378109"},{"title":"第三百八十六章 ：王者归来","id":"2378112"},{"title":"第三百八十七章 帝国","id":"2378114"},{"title":"第三百八十八章：坚强","id":"2378116"},{"title":"一早起来……看到订阅下滑","id":"2378118"},{"title":"第三百八十九章 漆黑","id":"2378121"},{"title":"第三百九十章 ：阴曹地府的困境","id":"2378122"},{"title":"第三百九十一章 齐天大圣","id":"2378124"},{"title":"第三百九十二章 ：不欢之筵","id":"2378126"},{"title":"第三百九十三章 老九的烂摊子","id":"2378128"},{"title":"第三百九十四章：师徒","id":"2378130"},{"title":"第三百九十五章 ：玉帝的愤怒","id":"2378132"},{"title":"第三百九十六章 ：查阅生死簿","id":"2378133"},{"title":"第三百九十七章 ：真相","id":"2378135"},{"title":"第三百九十八章 ：真相（2）","id":"2378136"},{"title":"第三百九十九章 ：无路可走","id":"2378137"},{"title":"第四百章 ：回斜月三星洞","id":"2378138"},{"title":"第四百零一章 ：心中无佛","id":"2378140"},{"title":"第四百零二章 ：修不修才是重点","id":"2378142"},{"title":"第四百零三章 ：战事再起","id":"2378144"},{"title":"第四百零四章 ：兑现诺言","id":"2378146"},{"title":"第四百零五章 ：心事","id":"2378148"},{"title":"第四百零六章 ：三份喜帖","id":"2378150"},{"title":"第四百零七章 ：三方","id":"2378151"},{"title":"聊聊2月2日晚至2月3日的事","id":"2378154"},{"title":"第四百零八章 ：抢亲","id":"2378156"},{"title":"第四百零九章 ：谈一谈","id":"2378158"},{"title":"第四百一十章 ：祭","id":"2378160"},{"title":"第四百一十一章 大婚前夕","id":"2378165"},{"title":"第四百一十二章 ：暗战","id":"2378168"},{"title":"第四百一十三章 ：头发","id":"2378170"},{"title":"第四百一十四章 ：凋落的花","id":"2378172"},{"title":"第四百一十五章 风铃","id":"2378173"},{"title":"第四百一十六章：怎么回事","id":"2378175"},{"title":"开个单章不求月票","id":"2378176"},{"title":"第四百一十七章：我爱你","id":"2378178"},{"title":"第四百一十八章 ：疯狂","id":"2378180"},{"title":"第四百一十九章 ：灾难","id":"2378182"},{"title":"第四百二十章 ：质问","id":"2378184"},{"title":"第四百二十一章 ：过奈河","id":"2378186"},{"title":"第四百二十二章 ：地府","id":"2378188"},{"title":"第四百二十三章 ：玉帝的困局","id":"2378190"},{"title":"第四百二十四章 ：混乱","id":"2378191"},{"title":"第四百二十五章 ：天蓬之愿","id":"2378193"},{"title":"第四百二十六章 地仙之祖","id":"2378195"},{"title":"第四百二十七章 走漏","id":"2378196"},{"title":"第四百二十八章 僵持","id":"2378198"},{"title":"第四百二十九章：元始天尊","id":"2378202"},{"title":"第四百三十章：撤离","id":"2378203"},{"title":"第四百三十一章","id":"2378207"},{"title":"第四百三十一章：逃跑？","id":"2378209"},{"title":"第四百三十二章：信函","id":"2378210"},{"title":"第四百三十三章：天上地下","id":"2378213"},{"title":"第四百三十四章：谁想问","id":"2378215"},{"title":"地球人已经阻止不了甲鱼了！","id":"2378218"},{"title":"第四百三十四章：谪仙井","id":"2378220"},{"title":"第四百三十六章：梦魇的终结","id":"2378222"},{"title":"第四百三十七章：真正的诛仙剑阵","id":"2378224"},{"title":"第四百三十八章 困兽","id":"2378226"},{"title":"第四百三十九章 深海","id":"2378228"},{"title":"第四百四十章：深海（2）","id":"2378229"},{"title":"第四百四十一章：关门","id":"2378232"},{"title":"第四百四十二章：我来了","id":"2378233"},{"title":"第四百四十三章 法阵核心","id":"2378235"},{"title":"第四百四十四章 开门不杀","id":"2378237"},{"title":"第一次上镜，感觉不满意","id":"2378240"},{"title":"第四百四十五章 南天门内","id":"2378242"},{"title":"第四百四十六章 战斗开始了","id":"2378243"},{"title":"第四百四十七章 孤身","id":"2378247"},{"title":"第四百四十八章 诡异的佛门","id":"2378250"},{"title":"第四百四十九章 ：天劫降临","id":"2378251"},{"title":"第四百五十章 ：可以吗？","id":"2378253"},{"title":"第四百五十一章 ：收尸","id":"2378255"},{"title":"第四百五十二章 ：不用你教我","id":"2378257"},{"title":"第四百五十三章 石头","id":"2378258"},{"title":"第四百五十四章 ：结束了吗？","id":"2378260"},{"title":"第四百五十五章 ：末日","id":"2378262"},{"title":"第四百五十六章：兑现诺言","id":"2378264"},{"title":"第四百五十七章：九辰大阵","id":"2378266"},{"title":"第四百五十八章：灵位","id":"2378268"},{"title":"第四百五十九章：乱局","id":"2378270"},{"title":"今天断更","id":"2378272"},{"title":"第四百六十章：代价","id":"2378273"},{"title":"第四百六十一章：无处可去","id":"2678201"},{"title":"第四百六十二章：淡去的星辰","id":"2678202"},{"title":"《》生日啦！","id":"2678203"},{"title":"第四百六十三章 灵犀","id":"2679492"},{"title":"第四百六十四章 想去哪儿呢？","id":"2763188"},{"title":"第四百六十五章 ：面对面","id":"2974306"},{"title":"第四百六十六章 ：高明","id":"3081332"},{"title":"第四百六十七章 ：无极对无我","id":"3301568"},{"title":"第四百六十八章 ：归途","id":"3335347"},{"title":"第四百六十九章 ：相隔万里","id":"3377755"},{"title":"第四百七十章 ：约定","id":"3380643"},{"title":"第四百七十一章 ：破裂","id":"3410035"},{"title":"第四百七十二章 ：玄叶","id":"3437236"},{"title":"第四百七十三章 ：延缓","id":"3482933"},{"title":"第四百七十四章 ：无休止的战争","id":"3482934"},{"title":"第四百七十五章 道心所在","id":"3482935"},{"title":"第四百七十六章 剩下的","id":"3510504"},{"title":"第四百七十七章：恍惚","id":"3517408"},{"title":"第四百七十八章：结束，也是开始","id":"3530617"},{"title":"写于文过半部。","id":"3549389"},{"title":"第四百七十九章：谈","id":"3552797"},{"title":"第四百八十章 抗旨西行","id":"3559134"},{"title":"第四百八十一章 风雨欲来","id":"3570831"},{"title":"第四百八十二章 ：出山","id":"3578279"},{"title":"第四百八十三章：造访龙宫","id":"3580697"},{"title":"第四百八十四章 施主，请自重","id":"3582585"},{"title":"第四百八十五章 是不是背叛了","id":"3587507"},{"title":"第四百八十六章 ：送信","id":"3587795"},{"title":"第四百八十七章 ：应对","id":"3599542"},{"title":"第四百八十八章 ：你被征用了","id":"3612997"},{"title":"第四百八十九章 ：被征用的好处","id":"3625332"},{"title":"第四百九十章 :清心 大章","id":"3650704"},{"title":"第四百九十一章 ：面谈","id":"3813582"},{"title":"第四百九十二章：观音禅院","id":"3813583"},{"title":"第四百九十三章：没人赢","id":"3813584"},{"title":"感谢~","id":"3854484"},{"title":"第四百九十四章：黑熊精","id":"3863399"},{"title":"通知一下~","id":"3874019"},{"title":"第四百九十五章：泄露","id":"3885391"},{"title":"第四百九十六章：迎接","id":"3915890"},{"title":"对于DT的某些言论。","id":"3938593"},{"title":"第四百九十七章 ：吕六拐","id":"3955834"},{"title":"最后发个单章，以后尽可能不发了。","id":"3964741"},{"title":"第四百九十八章：讲经","id":"3970126"},{"title":"第四百九十九章 纳婿","id":"3991089"},{"title":"第五百章 仇人见面","id":"3994728"},{"title":"第五百零一章 开打了","id":"3996027"},{"title":"第五百零二章 ：秘密","id":"4008177"},{"title":"第五百零三章：局","id":"4011040"},{"title":"第五百零四章：婚礼","id":"4023041"},{"title":"第五百零五章 ：现形","id":"4027989"},{"title":"第五百零六章 懦夫","id":"4031355"},{"title":"第五百零七章 取经人？","id":"4038408"},{"title":"第五百零八章 争执","id":"4048150"},{"title":"第五百零九章 和尚说谎","id":"4057503"},{"title":"第五百一十章 ：包容与忍让","id":"4066520"},{"title":"第五百一十一章 ：流沙河","id":"4075024"},{"title":"第五百一十二章：过河","id":"4078976"},{"title":"第五百一十三章：红孩儿","id":"4083401"},{"title":"第五百一十四章：五庄观","id":"4095063"},{"title":"第五百一十五章：村庄","id":"4102862"},{"title":"第五百一十六章：骗局","id":"4136695"},{"title":"第五百一十七章：绕开？","id":"4139932"},{"title":"第五百一十八章：被发现了","id":"4139946"},{"title":"第五百一十九章：镇元子的决定","id":"4208629"},{"title":"第五百二十章：五庄观","id":"4229268"},{"title":"第五百二十一章：人参果","id":"4238082"},{"title":"第五百二十二章：两个选择","id":"4248603"},{"title":"第五百二十三章：上古大妖","id":"4254436"},{"title":"第五百二十四章：闻风而动","id":"4266824"},{"title":"第五百二十五章：后手","id":"4280627"},{"title":"第五百二十六章：结义","id":"4288134"},{"title":"第五百二十七章：小白龙家到了","id":"4362449"},{"title":"第五百二十八章：失踪的白素","id":"4362450"},{"title":"第五百二十九章：南天门","id":"4386383"},{"title":"第五百三十章：兜率宫","id":"4411024"},{"title":"第五百三十一章：宝象国","id":"4468548"},{"title":"第五百三十二章 ：妖怪驸马爷","id":"4503097"},{"title":"第五百三十三章 :夜探驸马府","id":"4528928"},{"title":"第五百三十四章 ：混战","id":"4554579"},{"title":"第五百三十五章：不同意","id":"4578249"},{"title":"第五百三十六章 :角木蛟的烦恼","id":"4608345"},{"title":"第五百三十七章 ：奎木狼的处境","id":"4654303"},{"title":"第五百三十八章 ：花猴子","id":"4654304"},{"title":"第五百三十九章：临终遗言【求月票】","id":"4676972"},{"title":"第五百四十章：改变主意【求月票】","id":"4686979"},{"title":"第五百四十一章：珠子","id":"4700341"},{"title":"第五百四十二章：李靖的邀请【求月票】","id":"4743187"},{"title":"第五百四十三章：花果山上","id":"4743188"},{"title":"第五百四十四章：陷阱","id":"4762019"},{"title":"第五百四十五章：化缘","id":"4810146"},{"title":"第五百四十六章 普渡之道","id":"4810147"},{"title":"第五百四十七章：追寻","id":"4819892"},{"title":"第五百四十八章：梦境【求月票】","id":"4837026"},{"title":"第五百四十九章：修养","id":"4845733"},{"title":"第五百五十章：华山","id":"4900813"},{"title":"第五百五十一章：乌鸡国","id":"4900814"},{"title":"第五百五十二章：卷帘？","id":"4900815"},{"title":"第五百五十三章：卷帘的烂摊子","id":"4918905"},{"title":"第五百五十四章：卷帘的烂摊子（2）","id":"4935410"},{"title":"第五百五十五章：找粮食","id":"4970573"},{"title":"第五百五十六章：奇怪的条件","id":"4998535"},{"title":"第五百五十七章：诡异的谈判","id":"5006218"},{"title":"第五百五十八章：恶化","id":"5026048"},{"title":"第五百五十九章：最后通牒","id":"5033174"},{"title":"第五百六十章：卷帘的困境","id":"5049617"},{"title":"第五百六十一章：猴子救场","id":"5065330"},{"title":"第五百六十二章：华山","id":"5065331"},{"title":"第五百六十三章：许愿与还愿","id":"5070668"},{"title":"第五百六十四章：圣婴大王","id":"5087521"},{"title":"第五百六十五章：圣婴大王2","id":"5122017"},{"title":"第五百六十六章：圣婴大王3","id":"5122018"},{"title":"第五百六十六章：牛魔王","id":"5157292"},{"title":"第五百六十八章：去还是不去","id":"5168350"},{"title":"第五百六十九章：有古怪","id":"5182792"},{"title":"第五百七十章：神仙姐姐","id":"5195932"},{"title":"第五百七十一章：等待","id":"5215517"},{"title":"第五百七十二章：黑水河","id":"5223483"},{"title":"第五百七十三章：陷阱","id":"5238274"},{"title":"第五百七十四章：作弊","id":"5260034"},{"title":"第五百七十五章：低估","id":"5269258"},{"title":"第五百七十六章：金身","id":"5294703"},{"title":"第五百七十七章：河边","id":"5305686"},{"title":"第五百七十八章：夜谈","id":"5369066"},{"title":"第五百七十九章：夙愿","id":"5431767"},{"title":"第五百八十章：用刑","id":"5481936"},{"title":"第五百八十一章：最后的办法","id":"5482147"},{"title":"第五百八十二章：等待","id":"5548525"},{"title":"第五百八十三章：农夫与蛇","id":"5567963"},{"title":"第五百八十四章：还是毒蛇","id":"5590527"},{"title":"第五百八十五章：骗局","id":"5611428"},{"title":"第五百八十六章 ：暴走的金身","id":"5638806"},{"title":"第五百八十七章：那孩子叫啥？","id":"5655298"},{"title":"第五百八十八章：纠结","id":"5682092"},{"title":"第五百八十九章：召唤","id":"5713907"},{"title":"第五百九十章：一模一样的脸","id":"5726116"},{"title":"第五百九十一章：车迟国","id":"5739524"},{"title":"第五百九十二章：伺机而动","id":"5750061"},{"title":"第五百九十三章：有古怪","id":"5758165"},{"title":"第五百九十四章：你帮谁？","id":"5766556"},{"title":"第五百九十五章：投降","id":"5775298"},{"title":"第五百九十六章：五毒八苦","id":"5790954"},{"title":"第五百九十七章：水","id":"5798596"},{"title":"第五百九十八章：硬着头皮","id":"5805419"},{"title":"第五百九十九章：问","id":"5822021"},{"title":"第六百章：他母亲死了？","id":"5822161"},{"title":"第六百零一章：真与假","id":"5894500"},{"title":"第六百零二章：下策","id":"5895580"},{"title":"第六百零三章 ：有何区别？","id":"5895581"},{"title":"第六百零四章：续命与黑色玉简","id":"5895582"},{"title":"第六百零五章：只要一个人的命","id":"5895583"},{"title":"第六百零六章：现实","id":"5895584"},{"title":"第六百零七章：一个不留","id":"5895585"},{"title":"第六百零八章：活腻了吗？","id":"5895586"},{"title":"第六百零九章：越快越好","id":"5895587"},{"title":"第六百一十章：女儿国境","id":"5895588"},{"title":"第六百一十一章：女儿国的妖物","id":"5895589"},{"title":"第六百一十二章：来者何人？","id":"5895590"},{"title":"第六百一十三章：女儿国的女王","id":"5895591"},{"title":"第六百一十四章：宴席","id":"5905778"},{"title":"第六百一十五章：陵","id":"5905779"},{"title":"第六百一十六章：黑影","id":"5905780"},{"title":"第六百一十七章：毒","id":"5905781"},{"title":"第六百一十八章：芸香的办法","id":"5905782"},{"title":"第六百一十九章：条件","id":"5905783"},{"title":"第六百二十章：谈不拢","id":"5905784"},{"title":"第六百二十一章 ：玉简","id":"5905785"},{"title":"第六百二十二章：求救","id":"5905786"},{"title":"第六百二十三章 ：解药","id":"5905787"},{"title":"第六百二十四章 ：目标，花果山","id":"5905788"},{"title":"第六百二十五章：停下","id":"5905789"},{"title":"第六百二十六章：证明","id":"5905790"},{"title":"第六百二十七章 ：孩子","id":"5905791"},{"title":"第六百二十八章 ：劝说","id":"5905792"},{"title":"第六百二十九章 ：尖啸","id":"5905793"},{"title":"第六百三十章：直上三十三重天","id":"5905794"},{"title":"第六百三十一章：闹剧","id":"5905795"},{"title":"第六百三十二章 ：猜想","id":"5905796"},{"title":"第六百三十三章：沙与水","id":"5905797"},{"title":"第六百三十四章 ：普渡之惑","id":"5905798"},{"title":"第六百三十五章：长大了","id":"5905799"},{"title":"第六百三十六章：六耳猕猴","id":"5905800"},{"title":"第六百三十七章：六耳猕猴（2）","id":"5905801"},{"title":"第六百三十八章：醉酒","id":"5905802"},{"title":"第六百三十九章：唯一的路","id":"5905803"},{"title":"第六百四十章 ：坠入深渊的灵魂","id":"5905804"},{"title":"第六百四十一章 ：礼物","id":"5905805"},{"title":"第六百四十二章：翡翠鸳鸯","id":"5905806"},{"title":"第六百四十三章：您是大圣爷？","id":"5905807"},{"title":"第六百四十四章：行动","id":"5905808"},{"title":"第六百四十五章：求法国","id":"5905809"},{"title":"第六百四十六章 ：疑惑","id":"5905810"},{"title":"第六百四十七章：伤","id":"6378145"},{"title":"第六百四十八章：疑","id":"6385264"},{"title":"第六百四十九章：辩","id":"6390782"},{"title":"第六百五十章 ：讨要棍法","id":"6395144"},{"title":"第六百五十一章 ：诸佛辩法？","id":"6397480"},{"title":"第六百五十二章 ：愿不愿意","id":"6402296"},{"title":"第六百五十三章：胜负与激化","id":"6407721"},{"title":"第六百五十四章：结盟","id":"6413482"},{"title":"第六百五十五章 ：落魄的猕猴王","id":"6416253"},{"title":"第六百五十六章：死穴","id":"6431536"},{"title":"第六百五十七章：普世之道","id":"6431537"},{"title":"第六百五十八章 ：疯狂的六耳","id":"6431538"},{"title":"第六百五十九章：伏击","id":"6434588"},{"title":"第六百六十章：逼宫","id":"6438237"},{"title":"第六百六十一章：我就是","id":"6442281"},{"title":"第六百六十二章：黑熊精的烦恼","id":"6446372"},{"title":"第六百六十三章：问答","id":"6449649"},{"title":"第六百六十四章：九龙神火罩","id":"6455565"},{"title":"第六百六十五章：道果","id":"6479806"},{"title":"告诉大家一个好消息~","id":"6483073"},{"title":"第六百六十六章：毁灭","id":"6485937"},{"title":"第六百六十七章：铁饼","id":"6491000"},{"title":"第六百六十八章：曝光","id":"6502372"},{"title":"第六百六十九章：信","id":"6506829"},{"title":"第六百七十章：心知","id":"6514578"},{"title":"第六百七十一章：选择","id":"6536656"},{"title":"第六百七十二章：狂笑","id":"6541615"},{"title":"第六百七十三章：彷徨","id":"6544773"},{"title":"年会照片已经公布啦~","id":"6545209"},{"title":"第六百七十四章：回去？","id":"6548557"},{"title":"第六百七十五章：疯了","id":"6552586"},{"title":"第六百七十六章：流言","id":"6557238"},{"title":"第六百七十七章：半个家长","id":"6560838"},{"title":"第六百七十八章：礼尚往来","id":"6564879"},{"title":"第六百七十九章：取代","id":"6572456"},{"title":"第六百八十章：孺子不可教","id":"6576513"},{"title":"第六百八十一章：“坐山观虎斗”","id":"6583360"},{"title":"第六百八十三章：胜负","id":"6591007"},{"title":"第六百八十四章：还缺一件","id":"6594981"},{"title":"第六百八十五章：通风报信","id":"6599041"},{"title":"第六百八十六章：激化","id":"6605753"},{"title":"第六百八十七章：围魏救赵","id":"6616361"},{"title":"第六百八十八章：随心铁杆兵","id":"6620151"},{"title":"第六百八十九章：弱点","id":"6625825"},{"title":"第六百九十章：偷袭","id":"6629527"},{"title":"第六百九十一章：驰援与变数","id":"6635533"},{"title":"第六百九十二章：冒充","id":"6638453"},{"title":"第六百九十三章：杨婵","id":"6643622"},{"title":"第六百九十四章：杨婵（2）","id":"6648713"},{"title":"第六百九十五章：杨婵（3）","id":"6653840"},{"title":"关于过年的更新","id":"6655530"},{"title":"第六百九十六章：杨婵的主意","id":"6672650"},{"title":"第六百九十七章：不要再亏欠","id":"6679767"},{"title":"第六百九十八章：犹豫","id":"6692590"},{"title":"第六百九十九章：一门之隔","id":"6695869"},{"title":"第七百章：毒计","id":"6702214"},{"title":"第七百零一章:打压","id":"6705712"},{"title":"第七百零二章：信","id":"6711956"},{"title":"第七百零三章：埋伏","id":"6719499"},{"title":"，第七百零四章：劝说","id":"6726626"},{"title":"第七百零五章：风铃来了","id":"6733368"},{"title":"第七百零六章：反悔","id":"6742399"},{"title":"第七百零七章：两个女人","id":"6752121"},{"title":"第七百零八章：啪啪啪","id":"6762946"},{"title":"第七百零九章：抉择","id":"6768815"},{"title":"第七百一十章：玄奘的回答","id":"6772547"},{"title":"第七百一十一章：鲶鱼","id":"6783602"},{"title":"第七百一十二章：浪费时间？","id":"6791730"},{"title":"第七百一十三章：说客","id":"6837559"},{"title":"第七百一十四章：筹备婚礼","id":"6852644"},{"title":"第七百一十五章：雨云","id":"6855282"},{"title":"第七百一十六章：谈一谈","id":"6860473"},{"title":"第七百一十七章：后手","id":"6873929"},{"title":"第七百一十八章：师徒","id":"6884087"},{"title":"第七百一十九章：拜会","id":"6892544"},{"title":"第七百二十章：原本的样子","id":"6901621"},{"title":"第七百二十一章：种子","id":"6919418"},{"title":"第七百二十二章：渡与不渡","id":"6927979"},{"title":"第七百二十三章：颤","id":"6940892"},{"title":"第七百二十四章：低吼声","id":"6954510"},{"title":"第七百二十五章：吸一点？","id":"6970505"},{"title":"第七百二十六章：死局","id":"6978092"},{"title":"第七百二十七章：疑心","id":"6985301"},{"title":"第七百二十八章：水","id":"6996027"},{"title":"第七百二十九章：新领地","id":"7002180"},{"title":"第七百三十章：大雷音寺","id":"7008073"},{"title":"第七百三十一章：雷音郡","id":"7014210"},{"title":"第七百三十二章：战与不战","id":"7023492"},{"title":"第七百三十三章：逃不过","id":"7026308"},{"title":"第七百三十四章：成不了佛","id":"7033801"},{"title":"第七百三十五章：祈福","id":"7039646"},{"title":"第七百三十六章：明知是计","id":"7045852"},{"title":"第七百三十七章：黑影","id":"7051808"},{"title":"第七百三十八章：彼此利用","id":"7060235"},{"title":"第七百三十九章：祈福台","id":"7068077"},{"title":"第七百四十章：故计重施","id":"7074146"},{"title":"第七百四十一章：摊开了","id":"7088954"},{"title":"第七百四十二章：离去","id":"7098179"},{"title":"第七百四十三章：离开","id":"7105760"},{"title":"第七百四十四章：师徒","id":"7115002"},{"title":"第七百四十五章：八百年的愤怒","id":"7124455"},{"title":"第七百四十六章：条件","id":"7132535"},{"title":"第七百四十七章：怒火","id":"7145078"},{"title":"第七百四十八章：螳螂捕蝉","id":"7150836"},{"title":"第七百四十九章：代价","id":"7157117"},{"title":"第七百五十章：聊一聊","id":"7167884"},{"title":"第七百五十一章：命运的原点","id":"7174810"},{"title":"第七百五十二章：风雨欲来","id":"7185018"},{"title":"第七百五十三章：选择","id":"7191376"},{"title":"第七百五十四章：愤怒","id":"7197422"},{"title":"第七百五十五章：疑","id":"7203800"},{"title":"第七百五十六章：争夺","id":"7207534"},{"title":"第七百五十七章：诱惑","id":"7240256"},{"title":"第七百五十八章：金箍","id":"7250927"},{"title":"第七百五十九章 ：因果","id":"7260737"},{"title":"第七百六十章 ：内乱","id":"7266411"},{"title":"第七百六十一章 ：谣言","id":"7272898"},{"title":"第七百六十二章 ：嫌疑","id":"7277880"},{"title":"第七百六十三章 ：目的","id":"7285281"},{"title":"第七百六十四章 ：猜疑","id":"7296520"},{"title":"第七百六十五章 ：连坐","id":"7304463"},{"title":"第七百六十六章 ：劫狱","id":"7312197"},{"title":"第七百六十七章：乱","id":"7332152"},{"title":"第七百六十八章：时机","id":"7339157"},{"title":"第七百六十九章：玩一会","id":"7352340"},{"title":"第七百七十章：恼怒","id":"7368304"},{"title":"第七百七十一章：博弈","id":"7378922"},{"title":"第七百七十二章：自己","id":"7385461"},{"title":"第七百七十三章：心性的考验","id":"7392232"},{"title":"第七百七十四章：预言","id":"7402020"},{"title":"第七百七十五章：真假美猴王","id":"7410746"},{"title":"第七百七十六章：光壁","id":"7414927"},{"title":"第七百七十七章：英雄的归宿","id":"7432490"},{"title":"第七百七十八章：由不得你","id":"7442200"},{"title":"第七百七十九章：红线","id":"7448627"},{"title":"第七百八十章：最后的西行路","id":"7455329"},{"title":"第七百八十一章：上路","id":"7463727"},{"title":"第七百八十二章：迎接","id":"7470190"},{"title":"第七百八十三章：另一个人","id":"7480724"},{"title":"第七百八十四章：一路向西","id":"7702719"},{"title":"第七百八十五章：百里","id":"7702720"},{"title":"第七百八十六章：不如成佛","id":"7702721"},{"title":"第七百八十七章：母亲","id":"7702722"},{"title":"第七百八十八章：承诺","id":"7702723"},{"title":"第七百八十九章：翡翠","id":"7702724"},{"title":"第七百九十章：天道无及","id":"7702725"},{"title":"第七百九十一章：一个时辰","id":"7702726"},{"title":"第七百九十二章：本性难移","id":"7702727"},{"title":"第七百九十三章：紧箍咒","id":"7702728"},{"title":"第七百九十四章：不对劲","id":"7702729"},{"title":"第七百九十五章：老君的机会","id":"7702730"},{"title":"第七百九十六章：远去","id":"7702731"},{"title":"第七百九十七章：成佛","id":"7702732"},{"title":"第七百九十八章：最后的选择","id":"7702733"},{"title":"第七百九十九章：结束","id":"7702734"},{"title":"第八百章：藏心石","id":"7702735"},{"title":"第八百零一章：倒驾慈航","id":"7895905"},{"title":"第八百零二章：新的纪元","id":"7895906"},{"title":"完本了。","id":"7896068"}]