[{"title":"第一章 采花贼管饭吗？","id":"1769671"},{"title":"第二章 采花贼和职业球员是绝配","id":"1769673"},{"title":"第三章 里斯本竞技（新书求一切！）","id":"1769675"},{"title":"第四章 挤奶龙爪手问世","id":"1769677"},{"title":"第五章 哥就是传说","id":"1769679"},{"title":"第六章 史上最牛球童","id":"1769680"},{"title":"第七章 威逼小弟","id":"1769682"},{"title":"第八章 比女人还女人","id":"1769684"},{"title":"第九章 一线队","id":"1769686"},{"title":"第十章 请你吃冰棒！","id":"1769688"},{"title":"第十一章 香艳的凝练","id":"1769689"},{"title":"第十二章 这不科学","id":"1769691"},{"title":"第十三章 哪来哪去","id":"1769693"},{"title":"第十四章 师徒同路","id":"1769695"},{"title":"第十五章 特殊出品","id":"1769697"},{"title":"第十六章 大人物到场（求推荐、收藏！）","id":"1769700"},{"title":"第十七章 他们不懂你","id":"1769702"},{"title":"第十八章 擦枪走火","id":"1769704"},{"title":"第十九章 初采成功","id":"1769705"},{"title":"第二十章 下一站！荷兰","id":"1769707"},{"title":"第二十一章 特殊教学","id":"1769709"},{"title":"第二十二章 阿贾克斯很牛（求一切！）","id":"1769712"},{"title":"第一章 经济舱不能坐（继续求一切！）","id":"1769714"},{"title":"第二章 还有这要求！","id":"1769716"},{"title":"第三章 人家不鸟你（求推荐、收藏！）","id":"1769718"},{"title":"第四章 风水轮流转","id":"1769720"},{"title":"第五章 这样的！会来试训？","id":"1769722"},{"title":"第六章 疯狗乱吠","id":"1769724"},{"title":"第七章 前提条件(求收藏！)","id":"1769726"},{"title":"第八章 几近签约","id":"1769728"},{"title":"第九章 彪悍的开场白（收藏！）","id":"1769730"},{"title":"第十章 试炼伊布","id":"1769734"},{"title":"第十一章 谁戏耍了谁！（第一章到！）","id":"1769736"},{"title":"第十二章 分会成立！（二更，求收！）","id":"1769738"},{"title":"第十三章 极品啊！","id":"1769740"},{"title":"第十四章 可儿到手（求推荐、收藏！）","id":"1769741"},{"title":"第十五章 偷香窃玉！","id":"1769743"},{"title":"第十六章 不走寻常路（求票、求收！）","id":"1769744"},{"title":"第十七章 野路子？","id":"1769746"},{"title":"第十八章 换汤不换药","id":"1769748"},{"title":"第十九章 永远的小乞丐","id":"1769750"},{"title":"第二十章 回归一线队（求收、求票！）","id":"1769752"},{"title":"第二十一章 教学赛","id":"1769755"},{"title":"第二十一章 不是惜花之人","id":"1769759"},{"title":"第二十三章 全新的体验","id":"1769760"},{"title":"第二十四章 打土豪(没收、没推该行动了)","id":"1769762"},{"title":"第二十五章 开局不利","id":"1769764"},{"title":"第二十六章 宿醉","id":"1769766"},{"title":"第二十七章 一场好戏","id":"1769768"},{"title":"第二十八章 必须惊艳（求一切！）","id":"1769770"},{"title":"第二十九章 兴奋过头","id":"1769771"},{"title":"第三十章 万般菊花开（求一切！）","id":"1769772"},{"title":"第三十一章 头顶脚踢","id":"1769774"},{"title":"第三十二章 谣言的起因（收藏！推荐！）","id":"1769776"},{"title":"第三十三章 意外的认可","id":"1769778"},{"title":"第三十四章 盯梢（求收、求票）","id":"1769781"},{"title":"第三十五章 偶像剧","id":"1769783"},{"title":"第三十六章 触动心弦","id":"1769784"},{"title":"第三十七章 这可不怪我","id":"1769786"},{"title":"第三十八章 谁采了谁（求收、求票）","id":"1769788"},{"title":"第三十九章 场外红牌","id":"1769790"},{"title":"第四十章 太黑了","id":"1769792"},{"title":"第四十一章 打造杀器","id":"1769795"},{"title":"第四十二章 大力水手","id":"1769797"},{"title":"第四十三章 幸运女神私生子？","id":"1769799"},{"title":"第四十四章 倒霉的总是伊布","id":"1769802"},{"title":"第四十五章 最后的疯狂","id":"1769805"},{"title":"第四十六章 疯狂还在继续","id":"1769809"},{"title":"第四十七章 大场面","id":"1769811"},{"title":"第四十八章 豪门的底气","id":"1769815"},{"title":"第四十九章 好戏刚开始！（求票，求收）","id":"1769816"},{"title":"第五十章 踢哭皮尔洛","id":"1769818"},{"title":"第五十一章 再用玄功","id":"1769820"},{"title":"第五十二章 上帝收妖啊！","id":"1769822"},{"title":"第五十三章 霸气侧漏（求推荐票！）","id":"1769824"},{"title":"第五十四章 看到差距","id":"1769826"},{"title":"第五十五章 亮剑","id":"1769828"},{"title":"第五十六章 哪儿？你也能射门","id":"1769830"},{"title":"第五十七章 25号下场","id":"1769832"},{"title":"第五十八章 太妖了","id":"1769835"},{"title":"第五十九章 架没打成","id":"1769836"},{"title":"第六十章 帝哥的决定（打赏加更）","id":"1769839"},{"title":"第六十一章 训练打造","id":"1769841"},{"title":"第六十二章 打闹（求收、求票）","id":"1769843"},{"title":"第六十三章 琼克爆发（1）","id":"1769845"},{"title":"第六十四章 琼克爆发（2）","id":"1769847"},{"title":"第六十五章 门德斯的计划","id":"1769849"},{"title":"第六十六章 集邮男","id":"1769850"},{"title":"第六十七章 诉苦大会","id":"1769852"},{"title":"第六十八章 没吃药吧","id":"1769854"},{"title":"第六十九章 红苹果女孩","id":"1769855"},{"title":"第七十章 败家娘们","id":"1769857"},{"title":"第七十一章 意外的感动","id":"1769860"},{"title":"第七十二章 别样的一夜","id":"1769864"},{"title":"第七十三章 不怕媒体跟踪","id":"1769866"},{"title":"第七十四章 来点不一样的","id":"1769869"},{"title":"第七十五章 进球的感觉","id":"1769873"},{"title":"第七十六章 不犯规？","id":"1769877"},{"title":"第七十七章 比赛很热闹","id":"1769880"},{"title":"第七十八章 压榨中前行","id":"1769884"},{"title":"第七十九章 好状态惹的祸","id":"1769888"},{"title":"第八十章 出征西班牙","id":"1769892"},{"title":"第八十一章 客场就不能出去","id":"1769895"},{"title":"第八十二章 两周","id":"1769899"},{"title":"第83章 做板凳","id":"1769903"},{"title":"第八十四章 完美回归","id":"1769907"},{"title":"第八十五章 又是模特？","id":"1769911"},{"title":"第八十六章 女色魔绑架案？","id":"1769914"},{"title":"第八十七章 杰西卡·艾尔芭","id":"1769917"},{"title":"第八十八章 强敌阿森纳","id":"1769920"},{"title":"第八十九章 替罪羊","id":"1769923"},{"title":"第九十章 前哨战","id":"1769928"},{"title":"第九十一章 被琼克耍了？","id":"1769929"},{"title":"第九十二章 赛前紧张？","id":"1769930"},{"title":"第九十三章 闪耀开场","id":"1769932"},{"title":"第九十四章 一个人的比赛","id":"1769935"},{"title":"第九十五章 不屈","id":"1769939"},{"title":"第九十六章 爽啊！","id":"1769941"},{"title":"第九十七章 腰","id":"1769944"},{"title":"第九十八章 出征英伦","id":"1769948"},{"title":"第九十九章 玩人中成长","id":"1769951"},{"title":"第100章 嘘声的好处","id":"1769953"},{"title":"第101章 踢多错多","id":"1769958"},{"title":"第102章 这球进了","id":"1769960"},{"title":"第103章 见猎心喜","id":"1769962"},{"title":"第104章 古堡迷情（上）","id":"1769964"},{"title":"第105章 古堡迷情（下）","id":"1769965"},{"title":"第106章 当红的代价","id":"1769966"},{"title":"第107 成败在此一举","id":"1769968"},{"title":"第108章 心魔作祟","id":"1769970"},{"title":"第109章 尽情宣泄","id":"1769972"},{"title":"第110章 响彻全场","id":"1769975"},{"title":"第111章 冠军之夜","id":"1769977"},{"title":"第112章 庆祝之夜（弱喊一声求收求票）","id":"1769979"},{"title":"第113章 商讨","id":"1769981"},{"title":"第114章 何去何从","id":"1769983"},{"title":"第115章 冠军颁奖","id":"1769986"},{"title":"第116章 倒霉伊布","id":"1769987"},{"title":"第117章 确认转会","id":"1769988"},{"title":"第118章 夜店风波","id":"1769994"},{"title":"第119章 肥水不流外人田（卷终）","id":"1769995"},{"title":"第1章 新的开始","id":"1769997"},{"title":"第2章 先去的警局","id":"1769999"},{"title":"第3章 这可怎么整","id":"1770003"},{"title":"第4章 家乡习俗？","id":"1770004"},{"title":"第5章 惩罚之夜","id":"1770006"},{"title":"第6章 下马威？","id":"1770010"},{"title":"第7章 谁给谁的下马威","id":"1770011"},{"title":"第8章 这小子只能智取","id":"1770014"},{"title":"第9章 本钱十足","id":"1770015"},{"title":"第10章 能算我一个吗","id":"1770017"},{"title":"第11章 土豪切尔西","id":"1770019"},{"title":"第12章 土豪在行动（春节快乐！）","id":"1770021"},{"title":"第13章 阿布版鸿门宴（上）","id":"1770023"},{"title":"第14章 阿布版鸿门宴（下）","id":"1770025"},{"title":"第十五章 救治阿布","id":"1770028"},{"title":"第16章 私生子？","id":"1770030"},{"title":"第17章 阿布给撑腰","id":"1770032"},{"title":"第18章 要干架","id":"1770033"},{"title":"第19章 外号由来","id":"1770035"},{"title":"第20章 魔兽VS变态","id":"1770037"},{"title":"第21章 魔兽小弟","id":"1770038"},{"title":"第22章 英超新格局","id":"1770039"},{"title":"第23章 坐替补席","id":"1770040"},{"title":"第24章 替补坐的不怨","id":"1770041"},{"title":"第25章 1球领先","id":"1770043"},{"title":"第26章 替补出场之疯跑","id":"1770045"},{"title":"第27章 替补出场之进球","id":"1770047"},{"title":"第28章 比赛最佳","id":"1770049"},{"title":"第29章 原来是路痴","id":"1770050"},{"title":"第30章 天生媚骨","id":"1770053"},{"title":"第31章 东窗事发","id":"1770055"},{"title":"第32章 坏事变好","id":"1770057"},{"title":"第33章 替补再进球","id":"1770059"},{"title":"第34章 预备队扬名","id":"1770061"},{"title":"第35章 琼克的新挑战","id":"1770063"},{"title":"第36章 加紧练习","id":"1770064"},{"title":"第37章 目标阿森纳","id":"1770066"},{"title":"第38章 逆天的节奏","id":"1770068"},{"title":"第39章 第一次首发","id":"1770070"},{"title":"第40章 又见大力神轰门","id":"1770071"},{"title":"第41章 技惊四座","id":"1770073"},{"title":"第42章 25号最有威胁","id":"1770076"},{"title":"第43章 球星之路","id":"1770079"},{"title":"第44章 点缀星光","id":"1770084"},{"title":"第45章 星光加身","id":"1770087"},{"title":"第46章 换一种玩法","id":"1770089"},{"title":"第47章 这才有点像采花贼","id":"1770096"},{"title":"第48章 他应该首发","id":"1770098"},{"title":"第49章 主帅和球员都不受控制","id":"1770101"},{"title":"第50章 红牌不要钱","id":"1770103"},{"title":"第51章 怒砸更衣室","id":"1770105"},{"title":"第52章 阿布的疯狂","id":"1770106"},{"title":"第53章 打造的开始（求一切！）","id":"1770108"},{"title":"第54章 征召前夕","id":"1770112"},{"title":"第55章 别样的突然征召","id":"1770114"},{"title":"第56章 电话终于来了！（第二更求一切）","id":"1770116"},{"title":"第57章 美女轮盘","id":"1770118"},{"title":"第58章 不会吧！","id":"1770120"},{"title":"第59章 接受访问","id":"1770122"},{"title":"第60章 无解的射门","id":"1770125"},{"title":"第61章 PK佩佩（上）","id":"1770129"},{"title":"第62章 PK佩佩（下）","id":"1770133"},{"title":"第63章 不打不相识","id":"1770135"},{"title":"第64章 别样的护士","id":"1770138"},{"title":"第65章 让你们记住","id":"1770145"},{"title":"第66章 他叫琼克","id":"1770149"},{"title":"第67章 国家队风波","id":"1770153"},{"title":"第68章 疯狂的比赛","id":"1770155"},{"title":"第69章 包养的节奏？","id":"1770156"},{"title":"第70章 技术很好啊！","id":"1770158"},{"title":"第71章 拒绝厄运","id":"1770162"},{"title":"第72章 抉择","id":"1770166"},{"title":"第73章 出征俄罗斯","id":"1770169"},{"title":"第74章 恶劣的天气","id":"1770172"},{"title":"第75章 艰苦之战","id":"1770174"},{"title":"第76章 支持不够","id":"1770175"},{"title":"第77章 遭到羞辱","id":"1770176"},{"title":"第78章 回敬","id":"1770178"},{"title":"第79章 独中两元","id":"1770181"},{"title":"第80章 会是谁？","id":"1770183"},{"title":"第81章 终极大奖","id":"1770185"},{"title":"第82章 有代言？","id":"1770187"},{"title":"第83章 意外来客","id":"1770189"},{"title":"第84章 天才间的碰撞","id":"1770191"},{"title":"第85章 一场大胜","id":"1770193"},{"title":"第86章 一片大好","id":"1770195"},{"title":"第87章 场外因素","id":"1770198"},{"title":"第88章 不知真相的琼克","id":"1770202"},{"title":"第89章 停赛风波","id":"1770206"},{"title":"第90章 办公室风云","id":"1770208"},{"title":"第91章 消失后的大胜","id":"1770211"},{"title":"第92章 杀手来了","id":"1770213"},{"title":"第93章 伦敦大战前","id":"1770217"},{"title":"第94章 两大核心","id":"1770224"},{"title":"第95章 独自训练","id":"1770226"},{"title":"第96章 兴师问罪（求首订！）","id":"1770227"},{"title":"第91章 琼克归队（二更求一切！）","id":"1770229"},{"title":"第98章 回归第一波","id":"1770232"},{"title":"第99章 穆里尼奥的圈套（第二更送上！）","id":"1770234"},{"title":"第100章 害羞的琼克","id":"1770237"},{"title":"第101章 口水仗","id":"1770238"},{"title":"第102章 出征安菲尔德","id":"1770241"},{"title":"第103章 魔力鸟 （求支持，拜谢！）","id":"1770243"},{"title":"第104章 运气很重要","id":"1770245"},{"title":"第105章 新年聚会（上）","id":"1770249"},{"title":"第106章 新年聚会（下）","id":"1770252"},{"title":"第107章 扩大优势","id":"1770255"},{"title":"第108章 战红魔","id":"1770257"},{"title":"第109章 开窍？","id":"1770262"},{"title":"第110章 无声的挑战","id":"1770264"},{"title":"第111章 不死小强","id":"1770265"},{"title":"第112章 对决硬汉","id":"1770266"},{"title":"第113章 小宇宙爆发","id":"1770269"},{"title":"第114章 蜻蜓点水","id":"1770271"},{"title":"第115章 雄鹰出世","id":"1770276"},{"title":"第116章 恐怖的红魔","id":"1770279"},{"title":"第117章 那一抹的风采","id":"1770281"},{"title":"第118章 礼尚往来","id":"1770283"},{"title":"第119章 切尔西的春天","id":"1770285"},{"title":"第120章 粗野的对手","id":"1770288"},{"title":"第121章 质疑","id":"1770290"},{"title":"第122章 巧遇小魔女","id":"1770293"},{"title":"第123章 琼克跑了","id":"1770296"},{"title":"第124章 看比赛的门道","id":"1770299"},{"title":"第125章 老人的信心（求一切！）","id":"1770301"},{"title":"第126章 第一座奖杯","id":"1770303"},{"title":"第127章 出人意料的首发","id":"1770305"},{"title":"第128章 大战将起","id":"1770310"},{"title":"第129章 奇兵琼克","id":"1770311"},{"title":"第130章 对手巴萨","id":"1770312"},{"title":"第131章 坑你没商量","id":"1770313"},{"title":"第132章 风云变幻","id":"1770314"},{"title":"第133章 要命的上半时","id":"1770315"},{"title":"第134章 巴萨门神","id":"1770316"},{"title":"第135章 球队救世主","id":"1770318"},{"title":"第136章 别样的庆祝","id":"1770320"},{"title":"第137章 对比巨星","id":"1770322"},{"title":"第138章 代言来袭","id":"1770323"},{"title":"第139章 劲爆赌约（求一切！）","id":"1770325"},{"title":"第140章 没有后悔药","id":"1770326"},{"title":"第141章 买一送一","id":"1770327"},{"title":"第142章 赌约第一轮","id":"1770328"},{"title":"第143章 严厉的禁赛","id":"1770331"},{"title":"第144章 大胜拜仁","id":"1770333"},{"title":"第145章 令人期待的赌约","id":"1770337"},{"title":"第146章 不是也是的烟雾弹","id":"1770341"},{"title":"第147章 进军半决赛","id":"1770344"},{"title":"第148章 疯狂的第三季赌约","id":"1770348"},{"title":"第149章 女神你们就别想了","id":"1770350"},{"title":"第150章 小小的遗憾","id":"1770357"},{"title":"第151章 出名的代价","id":"1770361"},{"title":"第152章 夺冠之前夜（求一切！）","id":"1770371"},{"title":"第153章 夺冠之琼克的反击","id":"1770373"},{"title":"第154章 英超冠军","id":"1770376"},{"title":"第155章 遗憾中前行","id":"1770378"},{"title":"第156章 实至名归的捧杀","id":"1770379"},{"title":"第157章 英超收官","id":"1770382"},{"title":"第158章 又是一场要人命的比赛","id":"1770385"},{"title":"第159章 韩国之行","id":"1770386"},{"title":"第160章 神与白痴的综合体（求一切！）","id":"1770388"},{"title":"第161章 迈阿密风情","id":"1770391"},{"title":"第162章 忽冷忽热的夏天","id":"1770393"},{"title":"第163章 四强逐鹿","id":"1770395"},{"title":"第164章 黄金搭档","id":"1770397"},{"title":"第165章 奇葩组合","id":"1770400"},{"title":"第166章 意外之喜","id":"1770402"},{"title":"第167章 欧冠的宿命","id":"1770404"},{"title":"第168章 来去匆匆","id":"1770406"},{"title":"第169章 准备复仇","id":"1770408"},{"title":"第170章 史上最疯狂的首发","id":"1770410"},{"title":"第171章 以牙还牙","id":"1770413"},{"title":"第172章 今夜天使降临","id":"1770417"},{"title":"第173章 可敬的对手（高喊求一切！）","id":"1770419"},{"title":"第174章 主职副业的烦恼","id":"1770421"},{"title":"第175章 恋情","id":"1770424"},{"title":"第176章 豪取8连胜","id":"1770426"},{"title":"第177章 英超一枝独秀","id":"1770428"},{"title":"第178章 乐极生悲","id":"1770430"},{"title":"第179章 绯闻","id":"1770432"},{"title":"第180章 豪门窘境之战前","id":"1770435"},{"title":"第181章 豪门窘境之魔性","id":"1770436"},{"title":"第182章 蜕变","id":"1770438"},{"title":"第183章 蛮干","id":"1770439"},{"title":"第184章 好运不再","id":"1770440"},{"title":"第185章 解疑答惑（求一切！）","id":"1770443"},{"title":"第186章 席卷华夏","id":"1770445"},{"title":"第187章 红军又来了","id":"1770448"},{"title":"第188章 进球没算","id":"1770452"},{"title":"第189章 另外的冤家","id":"1770454"},{"title":"第190章 打破宁静","id":"1770457"},{"title":"第191章 对阵兵工厂","id":"1770463"},{"title":"第192章 倒挂金钩","id":"1770467"},{"title":"第193章 圣诞那点事","id":"1770470"},{"title":"第194章 两个人的圣诞","id":"1770473"},{"title":"第195章 天外飞仙","id":"1770475"},{"title":"第196章 切尔西人的圣诞","id":"1770477"},{"title":"第197章 恐怖片","id":"1770479"},{"title":"第198章 悲催的乔科尔","id":"1770481"},{"title":"第199章 转会传闻","id":"1770485"},{"title":"第200章 胜利背后的假摔","id":"1770489"},{"title":"第201章 第一场大败","id":"1770492"},{"title":"第202章 巴萨战前","id":"1770494"},{"title":"第203章 战","id":"1770497"},{"title":"第204章 战小罗","id":"1770499"},{"title":"第205章 琼克的反击","id":"1770503"},{"title":"第206章 鹿死谁手","id":"1770506"},{"title":"第207章 虐心之赛果","id":"1770509"},{"title":"第208章 小爷就是小爷","id":"1770511"},{"title":"第209章 欧冠出局","id":"1770513"},{"title":"第210章 忙里偷闲","id":"1770515"},{"title":"第211章 最后的拦路虎","id":"1770518"},{"title":"第212章 战红魔1","id":"1770520"},{"title":"第213 战红魔2","id":"1770522"},{"title":"第214 战红魔3","id":"1770525"},{"title":"第215 战红魔4","id":"1770526"},{"title":"第216 卫冕冠军","id":"1770529"},{"title":"第217 冠军后的失利","id":"1770532"},{"title":"第218 转会风波","id":"1770534"},{"title":"第219 三方追逐","id":"1770536"},{"title":"第220 英超落幕","id":"1770539"},{"title":"第221 最后的两场战役","id":"1770542"},{"title":"第222 世界杯分组","id":"1770544"},{"title":"第223 祸不单行","id":"1770548"},{"title":"第224 菲戈很牛","id":"1770552"},{"title":"第225 小胜第一轮","id":"1770555"},{"title":"第226 调整","id":"1770558"},{"title":"第227 大胜伊朗（1）","id":"1770560"},{"title":"第228 大胜伊朗（2）","id":"1770561"},{"title":"第229 大胜伊朗（3）","id":"1770563"},{"title":"第230 大胜晋级","id":"1770564"},{"title":"第231 悲催英格兰","id":"1770565"},{"title":"第232 想要吃橙子","id":"1770566"},{"title":"第233 世界杯16强","id":"1770567"},{"title":"第234 野蛮对冲（1）","id":"1770569"},{"title":"第235 野蛮对冲（2）","id":"1770570"},{"title":"第236 谁赢谁输","id":"1770578"},{"title":"第237 战前","id":"1770580"},{"title":"第238 四强","id":"1770588"},{"title":"第239 对手法国","id":"1770590"},{"title":"第240 半决赛","id":"1770593"},{"title":"第241 齐达内发力","id":"1770594"},{"title":"第242 琼克的回击","id":"1770595"},{"title":"第243 晋级决赛","id":"1770596"},{"title":"第244 意外的对手意大利","id":"1770599"},{"title":"第245 我们是世界杯冠军","id":"1770601"},{"title":"第1 小妖女","id":"1770604"},{"title":"第2 加盟AC米兰","id":"1770607"},{"title":"第3 初见","id":"1770609"},{"title":"第4 迫不及待","id":"1770610"},{"title":"第5 首战前","id":"1770612"},{"title":"第6 一军突起","id":"1770613"},{"title":"第7 锦上添花","id":"1770615"},{"title":"第8 势不可挡","id":"1770617"},{"title":"第9 欧冠分组","id":"1770618"},{"title":"第10 另类的办法","id":"1770619"},{"title":"第11 我会还的","id":"1770621"},{"title":"第12 隐形标王","id":"1770622"},{"title":"第13 这个广告可以拍","id":"1770623"},{"title":"第14 终于回正","id":"1770624"},{"title":"第15 偶遇","id":"1770626"},{"title":"第16 一夜**","id":"1770629"},{"title":"第17 铁树开花","id":"1770630"},{"title":"第18 米兰老年队","id":"1770632"},{"title":"第19 八卦来袭","id":"1770634"},{"title":"第20 战桑普","id":"1770636"},{"title":"第21 战桑普下","id":"1770639"},{"title":"第22 绝世组合","id":"1770643"},{"title":"第23 震惊的主席大人","id":"1770645"},{"title":"第24 闪耀全场","id":"1770646"},{"title":"第25 琼克伤后的米兰","id":"1770649"},{"title":"第26 起伏","id":"1770653"},{"title":"第27 传闻","id":"1770655"},{"title":"第28 意外获奖","id":"1770658"},{"title":"第29 东京之行","id":"1770661"},{"title":"第30 东京少女","id":"1770668"},{"title":"第31 终于有同伴了!","id":"1770676"},{"title":"第三十一 女仆!","id":"1770678"},{"title":"第32 征服女神","id":"1770682"},{"title":"第33 女仆到来","id":"1770686"},{"title":"第34 蹭吃组合","id":"1770691"},{"title":"第35 我就是我","id":"1770695"},{"title":"第36 这赌约很震撼","id":"1770697"},{"title":"第37 各方关注","id":"1770700"},{"title":"第38 像传奇一样","id":"1770705"},{"title":"第39 罗尼回归","id":"1770707"},{"title":"第40 完美回归","id":"1770710"},{"title":"第41 拿下","id":"1770713"},{"title":"第42 主席大人","id":"1770719"},{"title":"第43 和美女一起看房","id":"1770723"},{"title":"第44 屠戮","id":"1770725"},{"title":"第45 下一个对手拜仁","id":"1770728"},{"title":"第46 领先一球","id":"1770731"},{"title":"第47 装不下去了","id":"1770735"},{"title":"第48 英意大战","id":"1770738"},{"title":"第49 家有一老","id":"1770743"},{"title":"第50 兵不血刃","id":"1770747"},{"title":"第51 德比战前","id":"1770750"},{"title":"第52 这样的感觉真好","id":"1770756"},{"title":"第53 谁怕谁","id":"1770761"},{"title":"第54 对撞","id":"1770763"},{"title":"第55 鏖战马特拉济","id":"1770765"},{"title":"第56 为什么这样?","id":"1770767"},{"title":"第57 悬念横生","id":"1770770"},{"title":"第58 伊布发威","id":"1770775"},{"title":"第59 风水轮流转","id":"1770782"},{"title":"第60 追平进球纪录","id":"1770786"},{"title":"第61 闪耀","id":"1770789"},{"title":"第62 瞩目","id":"1770796"},{"title":"第63 欧冠唯一的悬念","id":"1770806"},{"title":"第64 晋级4强","id":"1770809"},{"title":"第65 皇马动心","id":"1770811"},{"title":"第66 冲向40大关","id":"1770813"},{"title":"第67 有所不为","id":"1770815"},{"title":"第68 艰苦赛程","id":"1770817"},{"title":"第69 陨落之星","id":"1770821"},{"title":"第70 出征英伦","id":"1770832"},{"title":"第71 无妄之灾","id":"1770840"},{"title":"第73 卡卡发力","id":"1770842"},{"title":"第74 琼克也给力","id":"1770843"},{"title":"第75 反超红魔","id":"1770844"},{"title":"第76 鏖战曼联","id":"1770845"},{"title":"第77 大战谢幕","id":"1770847"},{"title":"第78 等待对手犯错","id":"1770848"},{"title":"第79 穆里尼奥悬了","id":"1770850"},{"title":"第80 进军雅典","id":"1770852"},{"title":"第81 意甲的希望","id":"1770856"},{"title":"第82 两大核心的问题","id":"1770860"},{"title":"第83 各自准备","id":"1770862"},{"title":"第84 火热赛前","id":"1770863"},{"title":"第85 伟大的米兰","id":"1770864"},{"title":"第86 风云变幻","id":"1770865"},{"title":"第87 伟大时刻","id":"1770867"},{"title":"第88 欧冠效应","id":"1770869"},{"title":"第89 日了不该日的人","id":"1770871"},{"title":"第90 英德西的格局","id":"1770874"},{"title":"第91 豪门欧冠","id":"1770876"},{"title":"第92 续约风波","id":"1770877"},{"title":"第93 各方反应","id":"1770878"},{"title":"第94 转会传闻","id":"1770879"},{"title":"第95 华夏之行","id":"1770880"},{"title":"第96 这是要相亲啊!","id":"1770883"},{"title":"第97 剧情反转","id":"1770886"},{"title":"第98 不说就默认","id":"1770890"},{"title":"第99 曼联的逆袭","id":"1770891"},{"title":"第100 标王诞生","id":"1770895"},{"title":"第101 加盟曼联","id":"1770899"},{"title":"第102 你的练习生","id":"1770902"},{"title":"第103 英超转会","id":"1770911"},{"title":"第104 鲁尼有点懵","id":"1770912"},{"title":"第105 NANA来了","id":"1770914"},{"title":"第106 不再逃避","id":"1770924"},{"title":"第107 亚洲巡回赛","id":"1770925"},{"title":"第108 季前热身赛","id":"1770928"},{"title":"第109 看好曼联","id":"1770930"},{"title":"第110 首战雷丁","id":"1770932"},{"title":"第111 雷丁不是软柿子","id":"1770935"},{"title":"第112 我能试试吗?","id":"1770937"},{"title":"第113 打开进球账户","id":"1770939"},{"title":"第114 曼彻斯特德比战前","id":"1770942"},{"title":"第115 不走运的红魔","id":"1770951"},{"title":"第116 又见债主","id":"1770956"},{"title":"第117 倒霉的热刺","id":"1770966"},{"title":"第118 用进球说话","id":"1770969"},{"title":"第119 还有什么可质疑?","id":"1770973"},{"title":"第120 足球第一人","id":"1770982"},{"title":"第121 糟心事","id":"1770987"},{"title":"第122 疑似受罚","id":"1770991"},{"title":"第123 魔力鸟下课","id":"1770994"},{"title":"第124 战蓝军","id":"1770996"},{"title":"第125 团队核心","id":"1770998"},{"title":"第126 追平比分","id":"1771001"},{"title":"第127 国王的身影","id":"1771004"},{"title":"第128 稳居","id":"1771005"},{"title":"第129 渐入佳境","id":"1771006"},{"title":"第130 休闲娱乐","id":"1771007"},{"title":"第131 弗格森的点拨","id":"1771008"},{"title":"第132 禁赛期","id":"1771009"},{"title":"第133 平局收场","id":"1771010"},{"title":"第134 这假摔绝了","id":"1771011"},{"title":"第135 休闲活动","id":"1771012"},{"title":"第136 就是不从","id":"1771017"},{"title":"第137 想跑没地儿跑","id":"1771019"},{"title":"第138 弗格森的目标","id":"1771022"},{"title":"第139 四强逐鹿","id":"1771028"},{"title":"第140 圣诞头菜","id":"1771031"},{"title":"第141 新年英超","id":"1771034"},{"title":"第142 半程最佳","id":"1771036"},{"title":"第143 一票之差","id":"1771039"},{"title":"第144 冬季转会","id":"1771043"},{"title":"第145 欧冠淘汰赛","id":"1771046"},{"title":"第146 谁是兔爷？","id":"1771050"},{"title":"第147 愈战愈勇","id":"1771052"},{"title":"第148 闪耀全场","id":"1771056"},{"title":"第149 兵工厂来袭","id":"1771063"},{"title":"第150 慕尼黑空难","id":"1771066"},{"title":"第151 誓要进球","id":"1771068"},{"title":"第152 胜利的前奏","id":"1771071"},{"title":"第153 大胜的华彩","id":"1771074"},{"title":"第154 新杀器","id":"1771078"},{"title":"第155 那一脚的惊艳","id":"1771080"},{"title":"第156 两个平局","id":"1771081"},{"title":"第157 可怕的一周","id":"1771083"},{"title":"第158 早晚会反超","id":"1771085"},{"title":"第159 球星去约会","id":"1771088"},{"title":"第160 球星的情敌","id":"1771089"},{"title":"第161 请你去看球","id":"1771091"},{"title":"第162 冤家总是要聚首","id":"1771092"},{"title":"第163 琼克依赖症？","id":"1771093"},{"title":"第164 四强分水岭","id":"1771094"},{"title":"第165 轻取红军","id":"1771096"},{"title":"第166 冠军之路","id":"1771098"},{"title":"第167 红魔战红狼 1","id":"1771100"},{"title":"第168 红魔战红狼 2","id":"1771101"},{"title":"第169 必须进！！（祝大家新春快乐！）","id":"1771102"},{"title":"第170 天塌地陷","id":"1771105"},{"title":"第171 晋级半决赛","id":"1771109"},{"title":"第172 再胜兵工厂","id":"1771114"},{"title":"第173 不单单是一家俱乐部","id":"1771118"},{"title":"第174 战巴萨","id":"1771125"},{"title":"第175 这是假摔？","id":"1771127"},{"title":"第176 梅西发威","id":"1771129"},{"title":"第177 琼克的决心","id":"1771130"},{"title":"第178 逆袭","id":"1771132"},{"title":"第179 弗格森的一场豪赌","id":"1771133"},{"title":"第180 再战巴萨","id":"1771134"},{"title":"第181 无力回天","id":"1771138"},{"title":"第182 红蓝的对决","id":"1771142"},{"title":"第183 联赛冠军到手","id":"1771144"},{"title":"第184 非凡的球队","id":"1771146"},{"title":"第185 大战前夕","id":"1771148"},{"title":"第186 巅峰对决","id":"1771150"},{"title":"第187 激烈交锋","id":"1771151"},{"title":"第188 琼克的怒吼！","id":"1771152"},{"title":"第189 救主！","id":"1771154"},{"title":"第190 我们是冠军","id":"1771155"},{"title":"第191 请记住这个年轻人","id":"1771158"},{"title":"第192 葡萄牙国家队","id":"1771163"},{"title":"第193 我的祖国","id":"1771173"},{"title":"第194 乌鸦嘴","id":"1771176"},{"title":"第195 欧洲杯开战","id":"1771178"},{"title":"第196 首战开始","id":"1825352"},{"title":"第197 欧洲杯无二流","id":"2519479"},{"title":"第198 让伊比利亚半岛疯狂吧","id":"2519482"},{"title":"第199 疯狂还没有结束","id":"2519486"},{"title":"第200 首胜","id":"2519488"},{"title":"第201 胜利的烦恼","id":"2519491"},{"title":"第202 僵局的微笑","id":"2608283"},{"title":"第203 欢庆吧","id":"2678674"},{"title":"第204 德国来袭","id":"2706542"},{"title":"第205 斯科拉里要走了","id":"2933919"},{"title":"第206 大放水","id":"3057081"},{"title":"第207 葡德之战","id":"3210493"},{"title":"第208 葡德之战（貮）","id":"3324800"},{"title":"第209 葡德之战（叁）","id":"3368619"},{"title":"第210 胜利在望","id":"3396201"},{"title":"第211 黑马土耳其","id":"3435771"},{"title":"第212 俄罗斯进四强","id":"3452326"},{"title":"第213 西班牙的强大","id":"3461137"},{"title":"第214 黑马不再黑","id":"3467126"},{"title":"第215 搬家能管用？","id":"3481582"},{"title":"第216 这是战争","id":"3498740"},{"title":"第217 战争开始","id":"3508111"},{"title":"第218 微妙的战局","id":"3515141"},{"title":"第219 火在烧","id":"3521700"},{"title":"第220 点球大战","id":"3533944"},{"title":"第221 欧洲之王","id":"3543814"},{"title":"第222 凯旋","id":"3551191"},{"title":"第223 马不停蹄的表演赛","id":"3557101"},{"title":"第224 新赛季开始","id":"3562874"},{"title":"第225 疲劳期","id":"3569238"},{"title":"第226 赛季首冠","id":"3573955"},{"title":"第227 土豪来袭","id":"3577535"},{"title":"第228 预选赛开始","id":"3581437"},{"title":"第229 进球荒","id":"3584952"},{"title":"第230 一定要进！","id":"3592091"},{"title":"第231 危机时刻","id":"3612451"},{"title":"第232 该出手时就出手","id":"3621882"},{"title":"第233 都闭嘴吧！","id":"3629137"},{"title":"第234 新的发展计划","id":"3648877"},{"title":"第235 焦点之战","id":"3714179"},{"title":"第236 焦点之战（2）","id":"3714180"},{"title":"第237 焦点之战（3）","id":"3714182"},{"title":"第238 回敬对手","id":"3789430"},{"title":"第239 恶意犯规","id":"3825359"},{"title":"第240 债主来了","id":"3846880"},{"title":"第241 续约","id":"3861342"},{"title":"第242 基金会启动","id":"3872116"},{"title":"第243 两难啊","id":"3881482"},{"title":"第244 王牌对王牌","id":"3894109"},{"title":"第245 全新的德比","id":"3906924"},{"title":"第246 琼克队长","id":"3917006"},{"title":"第247 卫冕金球","id":"3933530"},{"title":"第248 闪耀时刻","id":"3951296"},{"title":"第249 惊魂白鹿巷","id":"3962274"},{"title":"第250 惊魂白鹿巷（2）","id":"3972383"},{"title":"第251 谋杀？","id":"3982244"},{"title":"第252 这是谋杀！","id":"3992422"},{"title":"第253 沸腾","id":"4004442"},{"title":"第254 严重的感冒","id":"4012399"},{"title":"第255 世界足球先生","id":"4019946"},{"title":"第256 风波渐起","id":"4028462"},{"title":"第257 培养新旗帜","id":"4034811"},{"title":"第258 伤愈","id":"4045680"},{"title":"第259 万众期待","id":"4055770"},{"title":"第260 回归首秀","id":"4065064"},{"title":"第261 王者归来","id":"4072525"},{"title":"第262 裁判成了主角","id":"4075717"},{"title":"第263 当然怒了","id":"4087725"},{"title":"第264 皇马的动作","id":"4087726"},{"title":"第265 空中幻想","id":"4092490"},{"title":"第266 无风起浪","id":"4100943"},{"title":"第267 一亿五千万？","id":"4118451"},{"title":"第268 复仇之战","id":"4136456"},{"title":"第269 还是那个琼克","id":"4160658"},{"title":"第270 巨星的风采","id":"4160659"},{"title":"第271 有了决定","id":"4184769"},{"title":"第272 曼联最后的比赛","id":"4204458"},{"title":"第273 对外公布","id":"4214292"},{"title":"第274 送别？","id":"4226719"},{"title":"第275 皇马？","id":"4234013"},{"title":"第276 劳尔的威胁","id":"4245155"},{"title":"第277 历史性身价","id":"4252028"},{"title":"第278 忠告","id":"4262605"},{"title":"第279 亮相伯纳乌","id":"4272787"},{"title":"第280 盛大的欢迎仪式","id":"4279590"},{"title":"第281 弗洛伦蒂诺模式","id":"4295420"},{"title":"第282 谁是主帅？","id":"4295421"},{"title":"第283 第一天的倒霉蛋","id":"4322734"},{"title":"第284 找错人了","id":"4322735"},{"title":"第285 皇马首秀","id":"4345664"},{"title":"第286 火热华夏","id":"4444362"},{"title":"第287 银河战舰第二期抵达","id":"4444413"},{"title":"第288 面子不是这么来的","id":"4464628"},{"title":"第290 不一样的助威","id":"4484011"},{"title":"第291 倒霉孩子","id":"4511580"},{"title":"第292 皇马的动作","id":"4511581"},{"title":"第293 五大锋线","id":"4525490"},{"title":"第289 巨星任意球大赛","id":"4545018"},{"title":"第294 佩佩的挑战","id":"4567586"},{"title":"第295 首战","id":"4587231"},{"title":"第296 琼克的演出","id":"4601800"},{"title":"第297 9号的传承","id":"4618270"},{"title":"第298 亚洲德比？","id":"4633474"},{"title":"第299 倒下吧！","id":"4649106"},{"title":"第300 新室友","id":"4666030"},{"title":"第301 欧冠首战","id":"4695607"},{"title":"第302 进球狂潮","id":"4715591"},{"title":"第303 门将危机","id":"4739780"},{"title":"第304 疯狂的比赛","id":"4756008"},{"title":"第305 疯狂的比赛（1）","id":"4771398"},{"title":"第306 疯狂的比赛（2）","id":"4783870"},{"title":"第307 疯狂的比赛（3）","id":"4798173"},{"title":"第308 琼疯狂","id":"4812731"},{"title":"第309 赛后余温","id":"4826343"},{"title":"第310 琼克时代","id":"4833977"},{"title":"第311 大战米兰","id":"4843243"},{"title":"第312 还是琼克","id":"4851524"},{"title":"第313 根本停不下来","id":"4863067"},{"title":"第314 进球机器","id":"4871518"},{"title":"第315 酒吧风波","id":"4884661"},{"title":"第316 盘外招","id":"4896836"},{"title":"第317 再战米兰","id":"4908142"},{"title":"第318 属于卡卡","id":"4917078"},{"title":"第319 僵持","id":"4923303"},{"title":"第320 站出来的还是他","id":"4932350"},{"title":"第321 马德里德比","id":"4983704"},{"title":"第322 火爆卡尔德隆","id":"4995797"},{"title":"第323 攻陷卡尔德隆","id":"5002064"},{"title":"第324 队长人选","id":"5009787"},{"title":"第325 不被看好的队长战","id":"5021376"},{"title":"第326 队长的带领","id":"5029708"},{"title":"第327 队长的力量","id":"5037367"},{"title":"第328 这才是队长","id":"5046731"},{"title":"第329 国家德比来袭","id":"5055608"},{"title":"第330 放豪言","id":"5076694"},{"title":"第331 真正的较量","id":"5093455"},{"title":"第332 绝不是豪言","id":"5114062"},{"title":"第333 激烈交锋","id":"5129166"},{"title":"第334 主角是裁判","id":"5138774"},{"title":"第335 重点照顾","id":"5149530"},{"title":"第336 水爷","id":"5166029"},{"title":"第337 永久的经典","id":"5178476"},{"title":"第338 梅西是小弟","id":"5191378"},{"title":"第339 颁奖典礼","id":"5200461"},{"title":"第340 豪门主教练不好当","id":"5212121"},{"title":"第341 炮轰主教练","id":"5220873"},{"title":"第342 横扫","id":"5231870"},{"title":"第343 该有个副业","id":"5245678"},{"title":"第344 巴斯克雄狮","id":"5256119"},{"title":"第345 斩雄狮","id":"5266694"},{"title":"第346 特里摊上大事了","id":"5279208"},{"title":"第347 给华夏球迷的祝语","id":"5290964"},{"title":"第348 没有他不行","id":"5301594"},{"title":"第349 决裂风暴","id":"5314443"},{"title":"第350 工程师很任性","id":"5363716"},{"title":"第351 任性的下场","id":"5420404"},{"title":"第352 走上正轨","id":"5463630"},{"title":"第353 德比前哨","id":"5480917"},{"title":"第354 去战斗","id":"5495175"},{"title":"第355 吉米蹦","id":"5537134"},{"title":"第356 火爆","id":"5561111"},{"title":"第357 追赶","id":"5585435"},{"title":"第358 红牌！被反超","id":"5608719"},{"title":"第359 火爆","id":"5633436"},{"title":"第360 他是血性!!","id":"5646439"},{"title":"第361 破纪录!","id":"5666581"},{"title":"第362 豪情万丈","id":"5680240"},{"title":"第363 最后的挣扎","id":"5691051"},{"title":"第364 彻底击沉巴萨","id":"5707337"},{"title":"第365 继续前进","id":"5723381"},{"title":"第366 还差一球!","id":"5731873"},{"title":"第367 笑逐颜开","id":"5738034"},{"title":"第368 追平纪录","id":"5748149"},{"title":"第369 看不见的对决","id":"5756096"},{"title":"第370 叫嚣的马洛卡","id":"5763339"},{"title":"第371 交锋","id":"5771640"},{"title":"第372 新的记录","id":"5780984"},{"title":"第373 向冠军冲刺","id":"5788603"},{"title":"第374 向冠军冲刺（1）","id":"5796286"},{"title":"第375 向冠军冲刺（2）","id":"5803166"},{"title":"第376 我们是冠军","id":"5812058"},{"title":"第377 欢庆","id":"5819765"},{"title":"第378 42球！","id":"5826694"},{"title":"第379 开始集训","id":"5833176"},{"title":"第380 热身赛","id":"5841510"},{"title":"第381 启程","id":"5849472"},{"title":"第382 冠军级的待遇","id":"5856077"},{"title":"第383 正式的队副","id":"5863457"},{"title":"第384 世界杯来了!","id":"5871401"},{"title":"第385 乌拉组啦","id":"5882197"},{"title":"第386 战前","id":"5884883"}]