[{"title":"第一章逃婚","id":"1318412"},{"title":"第二章车祸","id":"1318414"},{"title":"第三章魂移异界上","id":"1318416"},{"title":"第四章魂移医界下","id":"1318418"},{"title":"第五章","id":"1318422"},{"title":"第六章绝顶聪明的哑巴王子","id":"1318424"},{"title":"第七章莱雪公主","id":"1318426"},{"title":"第八章兽猎","id":"1318428"},{"title":"第九章原来你不是哑巴","id":"1318430"},{"title":"第十章武学奇才还是废材","id":"1318432"},{"title":"第十一章神秘老者上","id":"1318434"},{"title":"第十二章神秘老者下","id":"1318435"},{"title":"第十三章玄通镜","id":"1318437"},{"title":"第十四章领兵上阵(上)","id":"1318439"},{"title":"第十五章领兵上阵(中)","id":"1318442"},{"title":"第十六章领兵上阵(下)","id":"1318444"},{"title":"第十七章战前准备","id":"1318446"},{"title":"第十八章空中飞人","id":"1318448"},{"title":"第十九章大败敌兵上","id":"1318450"},{"title":"第二十章大败敌兵下","id":"1318452"},{"title":"第二十一章震惊维北区","id":"1318454"},{"title":"第二十二章一个消息","id":"1318456"},{"title":"第二十三章众城所归上","id":"1318458"},{"title":"第二十四章众城所归下","id":"1318460"},{"title":"第二十五章巴屈被虏上","id":"1318462"},{"title":"第二十六章巴屈被虏下","id":"1318465"},{"title":"第二十七章大获全胜","id":"1318467"},{"title":"第二十八章综汴羌王国","id":"1318469"},{"title":"第二十九章敌国被灭","id":"1318471"},{"title":"第三十章大清王国的危机","id":"1318473"},{"title":"第三十一章赶回","id":"1318476"},{"title":"第三十二章收服逝郑迪耶大王","id":"1318478"},{"title":"第三十三章再收服百万敌兵","id":"1318481"},{"title":"第三十四章将计就计","id":"1318482"},{"title":"第三十五章宴请帖","id":"1318484"},{"title":"第三十六章顺我者昌,逆我者亡","id":"1318486"},{"title":"第三十七章慑服","id":"1318488"},{"title":"第三十八章一统维北区","id":"1318490"},{"title":"第三十九章飞虎队","id":"1318492"},{"title":"第四十章特殊训练","id":"1318494"},{"title":"第四十一章维南区被统领","id":"1318496"},{"title":"第四十二章最后的准备","id":"1318498"},{"title":"第四十三章突破神龙战体","id":"1318501"},{"title":"第四十四章人玄士强者彝斯祁","id":"1318503"},{"title":"第四十五章初次相见","id":"1318505"},{"title":"第四十六章一箭定乾坤","id":"1318507"},{"title":"第四十七章轩辕三纹剑","id":"1318509"},{"title":"第四十八章血脉相连之三箭之威","id":"1318511"},{"title":"第四十九章维西区的消息","id":"1318513"},{"title":"第五十章维西区的特情","id":"1318516"},{"title":"第五十一章进军维西区","id":"1318518"},{"title":"第五十二章莱雪公主的相送","id":"1318520"},{"title":"第五十三章夜征三国","id":"1318522"},{"title":"第五十四章灭杀意外之敌","id":"1318524"},{"title":"第五十五章龙翔的愤怒与打赌","id":"1318526"},{"title":"第五十六章一个错误","id":"1318528"},{"title":"第五十七章灭杀屠尽敌兵","id":"1318530"},{"title":"第五十九章俗洛区的野心","id":"1318532"},{"title":"第六十章俗洛区的人玄士强者","id":"1318534"},{"title":"第六十一章夜征","id":"1318536"},{"title":"第六十二章维西区的最强联盟王国","id":"1318538"},{"title":"第六十三章震退","id":"1318541"},{"title":"第六十四章维西区内的第三位人玄士强者","id":"1318543"},{"title":"第六十五章三足鼎立","id":"1318545"},{"title":"第六十六章突破神龙战体中期","id":"1318547"},{"title":"第一百零三章俗维区的危机","id":"7005393"},{"title":"第一百零五章突破神龙战体圆满","id":"7005394"},{"title":"第一百零六章火速赶往俗维区","id":"7005395"},{"title":"第一百零七章大清王国被重重包围","id":"7005396"},{"title":"第一百零八章恐怖的防御光环","id":"7005397"},{"title":"第一百零九章王子殿下回来了","id":"7005398"},{"title":"第一百一十章血债要血偿","id":"7007384"},{"title":"第一百一十一章击溃众强者","id":"7013808"},{"title":"第一百一十二章击杀牧刹","id":"7092889"},{"title":"第一百一十三章邢卓的惊恐","id":"7135857"},{"title":"第一百一十四章探究玄通镜上","id":"7137430"},{"title":"第一百一十五章探究玄通镜中","id":"7150492"},{"title":"第一百一十六章探究玄通镜下","id":"7159762"},{"title":"第一百一十七章前人们的灵身","id":"7171149"},{"title":"第一百一十八章重建飞虎队","id":"7193807"},{"title":"第一百一十九章兽猎试比开始","id":"7249096"},{"title":"第一百二十章夺冠热门人选","id":"7259921"},{"title":"第一百二十一章进二级狩猎试比场","id":"7281266"},{"title":"第一百二十二章冠军","id":"7294675"},{"title":"第一百二十三章奖赏","id":"7309878"},{"title":"第一百二十四章惩罚","id":"7323111"},{"title":"第一百二十五章《懂你》","id":"7363538"},{"title":"第一百二十六章淬体","id":"7382871"},{"title":"第一百二十七章众组队进二级兽猎场借灵器","id":"7434598"},{"title":"第一百二十八章惊险","id":"7444855"},{"title":"第一百二十九章众将领突破人玄士","id":"7463241"},{"title":"第一百三十章沙暴谷","id":"7479685"},{"title":"第一百三十一章炼体神龙战体初期","id":"7496851"},{"title":"第一百三十二章踏上征途","id":"7562938"},{"title":"第一百三十三章那小恶魔来了","id":"7583790"},{"title":"第一百三十四章入主东刹","id":"7643664"},{"title":"第一百三十五章东洛","id":"7643665"},{"title":"第一百三十六章火爆的交易区","id":"7658945"},{"title":"一百三十七章三个蛋","id":"7707042"},{"title":"第一百三十八章乐土中邢","id":"7707043"},{"title":"第一百三十九章暗流云涌","id":"7777031"},{"title":"第一百四十章挑衅","id":"7836271"},{"title":"第一百四十一章获胜","id":"7965276"},{"title":"第一百四十二章公主出战","id":"8023285"},{"title":"第一百四十三章战起","id":"8089079"},{"title":"第一百四十四章东洛的实力","id":"8142561"},{"title":"第一百四十五章偷袭","id":"8174842"},{"title":"第一百四十六章黑衣人邑巴纳","id":"8192632"},{"title":"第一百四十七章地玄士强者","id":"8221019"},{"title":"第一百四十八章天地异象","id":"8236608"},{"title":"第一百四十九章暴翼炎龙突破四阶妖兽","id":"8252692"}]